Workbook

Sheet Dashboard
B2: Cash Management Controller
B3: Dashboard Overview • December 12, 2025
B5: Total Cash Position | D5: Pending Payments | F5: Active Time Deposits | H5: Overdue
B6: =CashTransactions!J2 | D6: =LET(status,PaymentsData!F:F,amounts,PaymentsData!D:D,SUMIF(status,"Pending",amounts)) | F6: =LET(status,DepositsData!G:G,principal,DepositsData!D:D,SUMIF(status,"Active",principal)) | H6: =COUNTIF(PaymentsData!F:F,"Overdue")
B8: Current Balance | D8: =LET(status,PaymentsData!F:F,COUNTIF(status,"Pending")&" payments") | F8: =LET(status,DepositsData!G:G,COUNTIF(status,"Active")&" deposits") | H8: Items
B10: Upcoming Payments (Next 7 Days) | G10: Maturing Deposits (Next 30 Days)
B11: Date | C11: Payee | D11: Amount | E11: Category | F11: Status | G11: Maturity | H11: Amount
B12: =LET( dates,PaymentsData!B2:B500, payees,PaymentsData!C2:C500, amounts,PaymentsData!D2:D500, categories,PaymentsData!E2:E500, statuses,PaymentsData!F2:F500, upcoming,FILTER(HSTACK(dates,payees,amounts,categories,statuses),(dates>=TODAY())*(dates<=TODAY()+7),""), sorted,SORT(upcoming,1,1), IFERROR(INDEX(sorted,1,1),"") ) | C12: =LET( dates,PaymentsData!B2:B500, payees,PaymentsData!C2:C500, amounts,PaymentsData!D2:D500, categories,PaymentsData!E2:E500, statuses,PaymentsData!F2:F500, upcoming,FILTER(HSTACK(dates,payees,amounts,categories,statuses),(dates>=TODAY())*(dates<=TODAY()+7),""), sorted,SORT(upcoming,1,1), IFERROR(INDEX(sorted,1,2),"") ) | D12: =LET( dates,PaymentsData!B2:B500, payees,PaymentsData!C2:C500, amounts,PaymentsData!D2:D500, categories,PaymentsData!E2:E500, statuses,PaymentsData!F2:F500, upcoming,FILTER(HSTACK(dates,payees,amounts,categories,statuses),(dates>=TODAY())*(dates<=TODAY()+7),""), sorted,SORT(upcoming,1,1), IFERROR(INDEX(sorted,1,3),"") ) | E12: =LET( dates,PaymentsData!B2:B500, payees,PaymentsData!C2:C500, amounts,PaymentsData!D2:D500, categories,PaymentsData!E2:E500, statuses,PaymentsData!F2:F500, upcoming,FILTER(HSTACK(dates,payees,amounts,categories,statuses),(dates>=TODAY())*(dates<=TODAY()+7),""), sorted,SORT(upcoming,1,1), IFERROR(INDEX(sorted,1,4),"") ) | F12: =LET( dates,PaymentsData!B2:B500, payees,PaymentsData!C2:C500, amounts,PaymentsData!D2:D500, categories,PaymentsData!E2:E500, statuses,PaymentsData!F2:F500, upcoming,FILTER(HSTACK(dates,payees,amounts,categories,statuses),(dates>=TODAY())*(dates<=TODAY()+7),""), sorted,SORT(upcoming,1,1), IFERROR(INDEX(sorted,1,5),"") ) | G12: =LET( maturity,DepositsData!F2:F100, principal,DepositsData!D2:D100, status,DepositsData!G2:G100, maturing,FILTER(HSTACK(maturity,principal),(maturity>=TODAY())*(maturity<=TODAY()+30)*(status="Active"),""), sorted,SORT(maturing,1,1), IFERROR(INDEX(sorted,1,1),"") ) | H12: =LET( maturity,DepositsData!F2:F100, principal,DepositsData!D2:D100, status,DepositsData!G2:G100, maturing,FILTER(HSTACK(maturity,principal),(maturity>=TODAY())*(maturity<=TODAY()+30)*(status="Active"),""), sorted,SORT(maturing,1,1), IFERROR(INDEX(sorted,1,2),"") )
B13: =LET( dates,PaymentsData!B2:B500, payees,PaymentsData!C2:C500, amounts,PaymentsData!D2:D500, categories,PaymentsData!E2:E500, statuses,PaymentsData!F2:F500, upcoming,FILTER(HSTACK(dates,payees,amounts,categories,statuses),(dates>=TODAY())*(dates<=TODAY()+7),""), sorted,SORT(upcoming,1,1), IFERROR(INDEX(sorted,2,1),"") ) | C13: =LET( dates,PaymentsData!B2:B500, payees,PaymentsData!C2:C500, amounts,PaymentsData!D2:D500, categories,PaymentsData!E2:E500, statuses,PaymentsData!F2:F500, upcoming,FILTER(HSTACK(dates,payees,amounts,categories,statuses),(dates>=TODAY())*(dates<=TODAY()+7),""), sorted,SORT(upcoming,1,1), IFERROR(INDEX(sorted,2,2),"") ) | D13: =LET( dates,PaymentsData!B2:B500, payees,PaymentsData!C2:C500, amounts,PaymentsData!D2:D500, categories,PaymentsData!E2:E500, statuses,PaymentsData!F2:F500, upcoming,FILTER(HSTACK(dates,payees,amounts,categories,statuses),(dates>=TODAY())*(dates<=TODAY()+7),""), sorted,SORT(upcoming,1,1), IFERROR(INDEX(sorted,2,3),"") ) | E13: =LET( dates,PaymentsData!B2:B500, payees,PaymentsData!C2:C500, amounts,PaymentsData!D2:D500, categories,PaymentsData!E2:E500, statuses,PaymentsData!F2:F500, upcoming,FILTER(HSTACK(dates,payees,amounts,categories,statuses),(dates>=TODAY())*(dates<=TODAY()+7),""), sorted,SORT(upcoming,1,1), IFERROR(INDEX(sorted,2,4),"") ) | F13: =LET( dates,PaymentsData!B2:B500, payees,PaymentsData!C2:C500, amounts,PaymentsData!D2:D500, categories,PaymentsData!E2:E500, statuses,PaymentsData!F2:F500, upcoming,FILTER(HSTACK(dates,payees,amounts,categories,statuses),(dates>=TODAY())*(dates<=TODAY()+7),""), sorted,SORT(upcoming,1,1), IFERROR(INDEX(sorted,2,5),"") ) | G13: =LET( maturity,DepositsData!F2:F100, principal,DepositsData!D2:D100, status,DepositsData!G2:G100, maturing,FILTER(HSTACK(maturity,principal),(maturity>=TODAY())*(maturity<=TODAY()+30)*(status="Active"),""), sorted,SORT(maturing,1,1), IFERROR(INDEX(sorted,2,1),"") ) | H13: =LET( maturity,DepositsData!F2:F100, principal,DepositsData!D2:D100, status,DepositsData!G2:G100, maturing,FILTER(HSTACK(maturity,principal),(maturity>=TODAY())*(maturity<=TODAY()+30)*(status="Active"),""), sorted,SORT(maturing,1,1), IFERROR(INDEX(sorted,2,2),"") )
B14: =LET( dates,PaymentsData!B2:B500, payees,PaymentsData!C2:C500, amounts,PaymentsData!D2:D500, categories,PaymentsData!E2:E500, statuses,PaymentsData!F2:F500, upcoming,FILTER(HSTACK(dates,payees,amounts,categories,statuses),(dates>=TODAY())*(dates<=TODAY()+7),""), sorted,SORT(upcoming,1,1), IFERROR(INDEX(sorted,3,1),"") ) | C14: =LET( dates,PaymentsData!B2:B500, payees,PaymentsData!C2:C500, amounts,PaymentsData!D2:D500, categories,PaymentsData!E2:E500, statuses,PaymentsData!F2:F500, upcoming,FILTER(HSTACK(dates,payees,amounts,categories,statuses),(dates>=TODAY())*(dates<=TODAY()+7),""), sorted,SORT(upcoming,1,1), IFERROR(INDEX(sorted,3,2),"") ) | D14: =LET( dates,PaymentsData!B2:B500, payees,PaymentsData!C2:C500, amounts,PaymentsData!D2:D500, categories,PaymentsData!E2:E500, statuses,PaymentsData!F2:F500, upcoming,FILTER(HSTACK(dates,payees,amounts,categories,statuses),(dates>=TODAY())*(dates<=TODAY()+7),""), sorted,SORT(upcoming,1,1), IFERROR(INDEX(sorted,3,3),"") ) | E14: =LET( dates,PaymentsData!B2:B500, payees,PaymentsData!C2:C500, amounts,PaymentsData!D2:D500, categories,PaymentsData!E2:E500, statuses,PaymentsData!F2:F500, upcoming,FILTER(HSTACK(dates,payees,amounts,categories,statuses),(dates>=TODAY())*(dates<=TODAY()+7),""), sorted,SORT(upcoming,1,1), IFERROR(INDEX(sorted,3,4),"") ) | F14: =LET( dates,PaymentsData!B2:B500, payees,PaymentsData!C2:C500, amounts,PaymentsData!D2:D500, categories,PaymentsData!E2:E500, statuses,PaymentsData!F2:F500, upcoming,FILTER(HSTACK(dates,payees,amounts,categories,statuses),(dates>=TODAY())*(dates<=TODAY()+7),""), sorted,SORT(upcoming,1,1), IFERROR(INDEX(sorted,3,5),"") ) | G14: =LET( maturity,DepositsData!F2:F100, principal,DepositsData!D2:D100, status,DepositsData!G2:G100, maturing,FILTER(HSTACK(maturity,principal),(maturity>=TODAY())*(maturity<=TODAY()+30)*(status="Active"),""), sorted,SORT(maturing,1,1), IFERROR(INDEX(sorted,3,1),"") ) | H14: =LET( maturity,DepositsData!F2:F100, principal,DepositsData!D2:D100, status,DepositsData!G2:G100, maturing,FILTER(HSTACK(maturity,principal),(maturity>=TODAY())*(maturity<=TODAY()+30)*(status="Active"),""), sorted,SORT(maturing,1,1), IFERROR(INDEX(sorted,3,2),"") )
B15: =LET( dates,PaymentsData!B2:B500, payees,PaymentsData!C2:C500, amounts,PaymentsData!D2:D500, categories,PaymentsData!E2:E500, statuses,PaymentsData!F2:F500, upcoming,FILTER(HSTACK(dates,payees,amounts,categories,statuses),(dates>=TODAY())*(dates<=TODAY()+7),""), sorted,SORT(upcoming,1,1), IFERROR(INDEX(sorted,4,1),"") ) | C15: =LET( dates,PaymentsData!B2:B500, payees,PaymentsData!C2:C500, amounts,PaymentsData!D2:D500, categories,PaymentsData!E2:E500, statuses,PaymentsData!F2:F500, upcoming,FILTER(HSTACK(dates,payees,amounts,categories,statuses),(dates>=TODAY())*(dates<=TODAY()+7),""), sorted,SORT(upcoming,1,1), IFERROR(INDEX(sorted,4,2),"") ) | D15: =LET( dates,PaymentsData!B2:B500, payees,PaymentsData!C2:C500, amounts,PaymentsData!D2:D500, categories,PaymentsData!E2:E500, statuses,PaymentsData!F2:F500, upcoming,FILTER(HSTACK(dates,payees,amounts,categories,statuses),(dates>=TODAY())*(dates<=TODAY()+7),""), sorted,SORT(upcoming,1,1), IFERROR(INDEX(sorted,4,3),"") ) | E15: =LET( dates,PaymentsData!B2:B500, payees,PaymentsData!C2:C500, amounts,PaymentsData!D2:D500, categories,PaymentsData!E2:E500, statuses,PaymentsData!F2:F500, upcoming,FILTER(HSTACK(dates,payees,amounts,categories,statuses),(dates>=TODAY())*(dates<=TODAY()+7),""), sorted,SORT(upcoming,1,1), IFERROR(INDEX(sorted,4,4),"") ) | F15: =LET( dates,PaymentsData!B2:B500, payees,PaymentsData!C2:C500, amounts,PaymentsData!D2:D500, categories,PaymentsData!E2:E500, statuses,PaymentsData!F2:F500, upcoming,FILTER(HSTACK(dates,payees,amounts,categories,statuses),(dates>=TODAY())*(dates<=TODAY()+7),""), sorted,SORT(upcoming,1,1), IFERROR(INDEX(sorted,4,5),"") ) | G15: =LET( maturity,DepositsData!F2:F100, principal,DepositsData!D2:D100, status,DepositsData!G2:G100, maturing,FILTER(HSTACK(maturity,principal),(maturity>=TODAY())*(maturity<=TODAY()+30)*(status="Active"),""), sorted,SORT(maturing,1,1), IFERROR(INDEX(sorted,4,1),"") ) | H15: =LET( maturity,DepositsData!F2:F100, principal,DepositsData!D2:D100, status,DepositsData!G2:G100, maturing,FILTER(HSTACK(maturity,principal),(maturity>=TODAY())*(maturity<=TODAY()+30)*(status="Active"),""), sorted,SORT(maturing,1,1), IFERROR(INDEX(sorted,4,2),"") )
B16: =LET( dates,PaymentsData!B2:B500, payees,PaymentsData!C2:C500, amounts,PaymentsData!D2:D500, categories,PaymentsData!E2:E500, statuses,PaymentsData!F2:F500, upcoming,FILTER(HSTACK(dates,payees,amounts,categories,statuses),(dates>=TODAY())*(dates<=TODAY()+7),""), sorted,SORT(upcoming,1,1), IFERROR(INDEX(sorted,5,1),"") ) | C16: =LET( dates,PaymentsData!B2:B500, payees,PaymentsData!C2:C500, amounts,PaymentsData!D2:D500, categories,PaymentsData!E2:E500, statuses,PaymentsData!F2:F500, upcoming,FILTER(HSTACK(dates,payees,amounts,categories,statuses),(dates>=TODAY())*(dates<=TODAY()+7),""), sorted,SORT(upcoming,1,1), IFERROR(INDEX(sorted,5,2),"") ) | D16: =LET( dates,PaymentsData!B2:B500, payees,PaymentsData!C2:C500, amounts,PaymentsData!D2:D500, categories,PaymentsData!E2:E500, statuses,PaymentsData!F2:F500, upcoming,FILTER(HSTACK(dates,payees,amounts,categories,statuses),(dates>=TODAY())*(dates<=TODAY()+7),""), sorted,SORT(upcoming,1,1), IFERROR(INDEX(sorted,5,3),"") ) | E16: =LET( dates,PaymentsData!B2:B500, payees,PaymentsData!C2:C500, amounts,PaymentsData!D2:D500, categories,PaymentsData!E2:E500, statuses,PaymentsData!F2:F500, upcoming,FILTER(HSTACK(dates,payees,amounts,categories,statuses),(dates>=TODAY())*(dates<=TODAY()+7),""), sorted,SORT(upcoming,1,1), IFERROR(INDEX(sorted,5,4),"") ) | F16: =LET( dates,PaymentsData!B2:B500, payees,PaymentsData!C2:C500, amounts,PaymentsData!D2:D500, categories,PaymentsData!E2:E500, statuses,PaymentsData!F2:F500, upcoming,FILTER(HSTACK(dates,payees,amounts,categories,statuses),(dates>=TODAY())*(dates<=TODAY()+7),""), sorted,SORT(upcoming,1,1), IFERROR(INDEX(sorted,5,5),"") ) | G16: =LET( maturity,DepositsData!F2:F100, principal,DepositsData!D2:D100, status,DepositsData!G2:G100, maturing,FILTER(HSTACK(maturity,principal),(maturity>=TODAY())*(maturity<=TODAY()+30)*(status="Active"),""), sorted,SORT(maturing,1,1), IFERROR(INDEX(sorted,5,1),"") ) | H16: =LET( maturity,DepositsData!F2:F100, principal,DepositsData!D2:D100, status,DepositsData!G2:G100, maturing,FILTER(HSTACK(maturity,principal),(maturity>=TODAY())*(maturity<=TODAY()+30)*(status="Active"),""), sorted,SORT(maturing,1,1), IFERROR(INDEX(sorted,5,2),"") )
B19: Cash Flow Summary
B20: Period | C20: Inflows | D20: Outflows | E20: Net Flow | F20: End Balance
B21: Today | C21: =CashFlowPositions!D4 | D21: =CashFlowPositions!E4 | E21: =CashFlowPositions!F4 | F21: =CashFlowPositions!G4
B22: This Week | C22: =CashFlowPositions!D5 | D22: =CashFlowPositions!E5 | E22: =CashFlowPositions!F5 | F22: =CashFlowPositions!G5
B23: This Month | C23: =CashFlowPositions!D6 | D23: =CashFlowPositions!E6 | E23: =CashFlowPositions!F6 | F23: =CashFlowPositions!G6
B24: Next 30 Days | C24: =CashFlowPositions!D7 | D24: =CashFlowPositions!E7 | E24: =CashFlowPositions!F7 | F24: =CashFlowPositions!G7
B27: Quick Navigation
B28: Payment Calendar | C28: Time Deposits | D28: Cash Flow Positions | E28: Settings

Sheet PaymentCalendar
B2: Payment Calendar
B4: Selected Month: | C4: December 2025
B6: Sunday | C6: Monday | D6: Tuesday | E6: Wednesday | F6: Thursday | G6: Friday | H6: Saturday
C7: 1 | D7: 2 | E7: 3 | F7: 4 | G7: 5 | H7: 6 | J7: Status Legend
C8: =LET( dates,PaymentsData!B2:B500, payees,PaymentsData!C2:C500, amounts,PaymentsData!D2:D500, dayPayments,FILTER(HSTACK(payees,amounts),DAY(dates)=1,""), IFERROR(INDEX(dayPayments,1,1)&" $"&TEXT(INDEX(dayPayments,1,2),"#,##0"),"") ) | D8: =LET( dates,PaymentsData!B2:B500, payees,PaymentsData!C2:C500, amounts,PaymentsData!D2:D500, dayPayments,FILTER(HSTACK(payees,amounts),DAY(dates)=2,""), IFERROR(INDEX(dayPayments,1,1)&" $"&TEXT(INDEX(dayPayments,1,2),"#,##0"),"") ) | E8: =LET( dates,PaymentsData!B2:B500, payees,PaymentsData!C2:C500, amounts,PaymentsData!D2:D500, dayPayments,FILTER(HSTACK(payees,amounts),DAY(dates)=3,""), IFERROR(INDEX(dayPayments,1,1)&" $"&TEXT(INDEX(dayPayments,1,2),"#,##0"),"") ) | F8: =LET( dates,PaymentsData!B2:B500, payees,PaymentsData!C2:C500, amounts,PaymentsData!D2:D500, dayPayments,FILTER(HSTACK(payees,amounts),DAY(dates)=4,""), IFERROR(INDEX(dayPayments,1,1)&" $"&TEXT(INDEX(dayPayments,1,2),"#,##0"),"") ) | G8: =LET( dates,PaymentsData!B2:B500, payees,PaymentsData!C2:C500, amounts,PaymentsData!D2:D500, dayPayments,FILTER(HSTACK(payees,amounts),DAY(dates)=5,""), IFERROR(INDEX(dayPayments,1,1)&" $"&TEXT(INDEX(dayPayments,1,2),"#,##0"),"") ) | H8: =LET( dates,PaymentsData!B2:B500, payees,PaymentsData!C2:C500, amounts,PaymentsData!D2:D500, dayPayments,FILTER(HSTACK(payees,amounts),DAY(dates)=6,""), IFERROR(INDEX(dayPayments,1,1)&" $"&TEXT(INDEX(dayPayments,1,2),"#,##0"),"") ) | J8: ● | K8: Paid
C9: =LET( dates,PaymentsData!B2:B500, payees,PaymentsData!C2:C500, amounts,PaymentsData!D2:D500, dayPayments,FILTER(HSTACK(payees,amounts),DAY(dates)=1,""), IFERROR(INDEX(dayPayments,2,1)&" $"&TEXT(INDEX(dayPayments,2,2),"#,##0"),"") ) | D9: =LET( dates,PaymentsData!B2:B500, payees,PaymentsData!C2:C500, amounts,PaymentsData!D2:D500, dayPayments,FILTER(HSTACK(payees,amounts),DAY(dates)=2,""), IFERROR(INDEX(dayPayments,2,1)&" $"&TEXT(INDEX(dayPayments,2,2),"#,##0"),"") ) | E9: =LET( dates,PaymentsData!B2:B500, payees,PaymentsData!C2:C500, amounts,PaymentsData!D2:D500, dayPayments,FILTER(HSTACK(payees,amounts),DAY(dates)=3,""), IFERROR(INDEX(dayPayments,2,1)&" $"&TEXT(INDEX(dayPayments,2,2),"#,##0"),"") ) | F9: =LET( dates,PaymentsData!B2:B500, payees,PaymentsData!C2:C500, amounts,PaymentsData!D2:D500, dayPayments,FILTER(HSTACK(payees,amounts),DAY(dates)=4,""), IFERROR(INDEX(dayPayments,2,1)&" $"&TEXT(INDEX(dayPayments,2,2),"#,##0"),"") ) | G9: =LET( dates,PaymentsData!B2:B500, payees,PaymentsData!C2:C500, amounts,PaymentsData!D2:D500, dayPayments,FILTER(HSTACK(payees,amounts),DAY(dates)=5,""), IFERROR(INDEX(dayPayments,2,1)&" $"&TEXT(INDEX(dayPayments,2,2),"#,##0"),"") ) | H9: =LET( dates,PaymentsData!B2:B500, payees,PaymentsData!C2:C500, amounts,PaymentsData!D2:D500, dayPayments,FILTER(HSTACK(payees,amounts),DAY(dates)=6,""), IFERROR(INDEX(dayPayments,2,1)&" $"&TEXT(INDEX(dayPayments,2,2),"#,##0"),"") ) | J9: ● | K9: Pending
C10: =LET( dates,PaymentsData!B2:B500, payees,PaymentsData!C2:C500, amounts,PaymentsData!D2:D500, dayPayments,FILTER(HSTACK(payees,amounts),DAY(dates)=1,""), IFERROR(INDEX(dayPayments,3,1)&" $"&TEXT(INDEX(dayPayments,3,2),"#,##0"),"") ) | D10: =LET( dates,PaymentsData!B2:B500, payees,PaymentsData!C2:C500, amounts,PaymentsData!D2:D500, dayPayments,FILTER(HSTACK(payees,amounts),DAY(dates)=2,""), IFERROR(INDEX(dayPayments,3,1)&" $"&TEXT(INDEX(dayPayments,3,2),"#,##0"),"") ) | E10: =LET( dates,PaymentsData!B2:B500, payees,PaymentsData!C2:C500, amounts,PaymentsData!D2:D500, dayPayments,FILTER(HSTACK(payees,amounts),DAY(dates)=3,""), IFERROR(INDEX(dayPayments,3,1)&" $"&TEXT(INDEX(dayPayments,3,2),"#,##0"),"") ) | F10: =LET( dates,PaymentsData!B2:B500, payees,PaymentsData!C2:C500, amounts,PaymentsData!D2:D500, dayPayments,FILTER(HSTACK(payees,amounts),DAY(dates)=4,""), IFERROR(INDEX(dayPayments,3,1)&" $"&TEXT(INDEX(dayPayments,3,2),"#,##0"),"") ) | G10: =LET( dates,PaymentsData!B2:B500, payees,PaymentsData!C2:C500, amounts,PaymentsData!D2:D500, dayPayments,FILTER(HSTACK(payees,amounts),DAY(dates)=5,""), IFERROR(INDEX(dayPayments,3,1)&" $"&TEXT(INDEX(dayPayments,3,2),"#,##0"),"") ) | H10: =LET( dates,PaymentsData!B2:B500, payees,PaymentsData!C2:C500, amounts,PaymentsData!D2:D500, dayPayments,FILTER(HSTACK(payees,amounts),DAY(dates)=6,""), IFERROR(INDEX(dayPayments,3,1)&" $"&TEXT(INDEX(dayPayments,3,2),"#,##0"),"") ) | J10: ● | K10: Scheduled
J11: ● | K11: Overdue
B12: 7 | C12: 8 | D12: 9 | E12: 10 | F12: 11 | G12: 12 | H12: 13 | J12: ● | K12: Cancelled
B13: =LET( dates,PaymentsData!B2:B500, payees,PaymentsData!C2:C500, amounts,PaymentsData!D2:D500, dayPayments,FILTER(HSTACK(payees,amounts),DAY(dates)=7,""), IFERROR(INDEX(dayPayments,1,1)&" $"&TEXT(INDEX(dayPayments,1,2),"#,##0"),"") ) | C13: =LET( dates,PaymentsData!B2:B500, payees,PaymentsData!C2:C500, amounts,PaymentsData!D2:D500, dayPayments,FILTER(HSTACK(payees,amounts),DAY(dates)=8,""), IFERROR(INDEX(dayPayments,1,1)&" $"&TEXT(INDEX(dayPayments,1,2),"#,##0"),"") ) | D13: =LET( dates,PaymentsData!B2:B500, payees,PaymentsData!C2:C500, amounts,PaymentsData!D2:D500, dayPayments,FILTER(HSTACK(payees,amounts),DAY(dates)=9,""), IFERROR(INDEX(dayPayments,1,1)&" $"&TEXT(INDEX(dayPayments,1,2),"#,##0"),"") ) | E13: =LET( dates,PaymentsData!B2:B500, payees,PaymentsData!C2:C500, amounts,PaymentsData!D2:D500, dayPayments,FILTER(HSTACK(payees,amounts),DAY(dates)=10,""), IFERROR(INDEX(dayPayments,1,1)&" $"&TEXT(INDEX(dayPayments,1,2),"#,##0"),"") ) | F13: =LET( dates,PaymentsData!B2:B500, payees,PaymentsData!C2:C500, amounts,PaymentsData!D2:D500, dayPayments,FILTER(HSTACK(payees,amounts),DAY(dates)=11,""), IFERROR(INDEX(dayPayments,1,1)&" $"&TEXT(INDEX(dayPayments,1,2),"#,##0"),"") ) | G13: =LET( dates,PaymentsData!B2:B500, payees,PaymentsData!C2:C500, amounts,PaymentsData!D2:D500, dayPayments,FILTER(HSTACK(payees,amounts),DAY(dates)=12,""), IFERROR(INDEX(dayPayments,1,1)&" $"&TEXT(INDEX(dayPayments,1,2),"#,##0"),"") ) | H13: =LET( dates,PaymentsData!B2:B500, payees,PaymentsData!C2:C500, amounts,PaymentsData!D2:D500, dayPayments,FILTER(HSTACK(payees,amounts),DAY(dates)=13,""), IFERROR(INDEX(dayPayments,1,1)&" $"&TEXT(INDEX(dayPayments,1,2),"#,##0"),"") )
B14: =LET( dates,PaymentsData!B2:B500, payees,PaymentsData!C2:C500, amounts,PaymentsData!D2:D500, dayPayments,FILTER(HSTACK(payees,amounts),DAY(dates)=7,""), IFERROR(INDEX(dayPayments,2,1)&" $"&TEXT(INDEX(dayPayments,2,2),"#,##0"),"") ) | C14: =LET( dates,PaymentsData!B2:B500, payees,PaymentsData!C2:C500, amounts,PaymentsData!D2:D500, dayPayments,FILTER(HSTACK(payees,amounts),DAY(dates)=8,""), IFERROR(INDEX(dayPayments,2,1)&" $"&TEXT(INDEX(dayPayments,2,2),"#,##0"),"") ) | D14: =LET( dates,PaymentsData!B2:B500, payees,PaymentsData!C2:C500, amounts,PaymentsData!D2:D500, dayPayments,FILTER(HSTACK(payees,amounts),DAY(dates)=9,""), IFERROR(INDEX(dayPayments,2,1)&" $"&TEXT(INDEX(dayPayments,2,2),"#,##0"),"") ) | E14: =LET( dates,PaymentsData!B2:B500, payees,PaymentsData!C2:C500, amounts,PaymentsData!D2:D500, dayPayments,FILTER(HSTACK(payees,amounts),DAY(dates)=10,""), IFERROR(INDEX(dayPayments,2,1)&" $"&TEXT(INDEX(dayPayments,2,2),"#,##0"),"") ) | F14: =LET( dates,PaymentsData!B2:B500, payees,PaymentsData!C2:C500, amounts,PaymentsData!D2:D500, dayPayments,FILTER(HSTACK(payees,amounts),DAY(dates)=11,""), IFERROR(INDEX(dayPayments,2,1)&" $"&TEXT(INDEX(dayPayments,2,2),"#,##0"),"") ) | G14: =LET( dates,PaymentsData!B2:B500, payees,PaymentsData!C2:C500, amounts,PaymentsData!D2:D500, dayPayments,FILTER(HSTACK(payees,amounts),DAY(dates)=12,""), IFERROR(INDEX(dayPayments,2,1)&" $"&TEXT(INDEX(dayPayments,2,2),"#,##0"),"") ) | H14: =LET( dates,PaymentsData!B2:B500, payees,PaymentsData!C2:C500, amounts,PaymentsData!D2:D500, dayPayments,FILTER(HSTACK(payees,amounts),DAY(dates)=13,""), IFERROR(INDEX(dayPayments,2,1)&" $"&TEXT(INDEX(dayPayments,2,2),"#,##0"),"") )
B15: =LET( dates,PaymentsData!B2:B500, payees,PaymentsData!C2:C500, amounts,PaymentsData!D2:D500, dayPayments,FILTER(HSTACK(payees,amounts),DAY(dates)=7,""), IFERROR(INDEX(dayPayments,3,1)&" $"&TEXT(INDEX(dayPayments,3,2),"#,##0"),"") ) | C15: =LET( dates,PaymentsData!B2:B500, payees,PaymentsData!C2:C500, amounts,PaymentsData!D2:D500, dayPayments,FILTER(HSTACK(payees,amounts),DAY(dates)=8,""), IFERROR(INDEX(dayPayments,3,1)&" $"&TEXT(INDEX(dayPayments,3,2),"#,##0"),"") ) | D15: =LET( dates,PaymentsData!B2:B500, payees,PaymentsData!C2:C500, amounts,PaymentsData!D2:D500, dayPayments,FILTER(HSTACK(payees,amounts),DAY(dates)=9,""), IFERROR(INDEX(dayPayments,3,1)&" $"&TEXT(INDEX(dayPayments,3,2),"#,##0"),"") ) | E15: =LET( dates,PaymentsData!B2:B500, payees,PaymentsData!C2:C500, amounts,PaymentsData!D2:D500, dayPayments,FILTER(HSTACK(payees,amounts),DAY(dates)=10,""), IFERROR(INDEX(dayPayments,3,1)&" $"&TEXT(INDEX(dayPayments,3,2),"#,##0"),"") ) | F15: =LET( dates,PaymentsData!B2:B500, payees,PaymentsData!C2:C500, amounts,PaymentsData!D2:D500, dayPayments,FILTER(HSTACK(payees,amounts),DAY(dates)=11,""), IFERROR(INDEX(dayPayments,3,1)&" $"&TEXT(INDEX(dayPayments,3,2),"#,##0"),"") ) | G15: =LET( dates,PaymentsData!B2:B500, payees,PaymentsData!C2:C500, amounts,PaymentsData!D2:D500, dayPayments,FILTER(HSTACK(payees,amounts),DAY(dates)=12,""), IFERROR(INDEX(dayPayments,3,1)&" $"&TEXT(INDEX(dayPayments,3,2),"#,##0"),"") ) | H15: =LET( dates,PaymentsData!B2:B500, payees,PaymentsData!C2:C500, amounts,PaymentsData!D2:D500, dayPayments,FILTER(HSTACK(payees,amounts),DAY(dates)=13,""), IFERROR(INDEX(dayPayments,3,1)&" $"&TEXT(INDEX(dayPayments,3,2),"#,##0"),"") ) | J15: Monthly Totals
J16: Scheduled: | K16: =LET(s,PaymentsData!F:F,a,PaymentsData!D:D,SUMIF(s,"Scheduled",a))
B17: 14 | C17: 15 | D17: 16 | E17: 17 | F17: 18 | G17: 19 | H17: 20 | J17: Pending: | K17: =LET(s,PaymentsData!F:F,a,PaymentsData!D:D,SUMIF(s,"Pending",a))
B18: =LET( dates,PaymentsData!B2:B500, payees,PaymentsData!C2:C500, amounts,PaymentsData!D2:D500, dayPayments,FILTER(HSTACK(payees,amounts),DAY(dates)=14,""), IFERROR(INDEX(dayPayments,1,1)&" $"&TEXT(INDEX(dayPayments,1,2),"#,##0"),"") ) | C18: =LET( dates,PaymentsData!B2:B500, payees,PaymentsData!C2:C500, amounts,PaymentsData!D2:D500, dayPayments,FILTER(HSTACK(payees,amounts),DAY(dates)=15,""), IFERROR(INDEX(dayPayments,1,1)&" $"&TEXT(INDEX(dayPayments,1,2),"#,##0"),"") ) | D18: =LET( dates,PaymentsData!B2:B500, payees,PaymentsData!C2:C500, amounts,PaymentsData!D2:D500, dayPayments,FILTER(HSTACK(payees,amounts),DAY(dates)=16,""), IFERROR(INDEX(dayPayments,1,1)&" $"&TEXT(INDEX(dayPayments,1,2),"#,##0"),"") ) | E18: =LET( dates,PaymentsData!B2:B500, payees,PaymentsData!C2:C500, amounts,PaymentsData!D2:D500, dayPayments,FILTER(HSTACK(payees,amounts),DAY(dates)=17,""), IFERROR(INDEX(dayPayments,1,1)&" $"&TEXT(INDEX(dayPayments,1,2),"#,##0"),"") ) | F18: =LET( dates,PaymentsData!B2:B500, payees,PaymentsData!C2:C500, amounts,PaymentsData!D2:D500, dayPayments,FILTER(HSTACK(payees,amounts),DAY(dates)=18,""), IFERROR(INDEX(dayPayments,1,1)&" $"&TEXT(INDEX(dayPayments,1,2),"#,##0"),"") ) | G18: =LET( dates,PaymentsData!B2:B500, payees,PaymentsData!C2:C500, amounts,PaymentsData!D2:D500, dayPayments,FILTER(HSTACK(payees,amounts),DAY(dates)=19,""), IFERROR(INDEX(dayPayments,1,1)&" $"&TEXT(INDEX(dayPayments,1,2),"#,##0"),"") ) | H18: =LET( dates,PaymentsData!B2:B500, payees,PaymentsData!C2:C500, amounts,PaymentsData!D2:D500, dayPayments,FILTER(HSTACK(payees,amounts),DAY(dates)=20,""), IFERROR(INDEX(dayPayments,1,1)&" $"&TEXT(INDEX(dayPayments,1,2),"#,##0"),"") ) | J18: Paid: | K18: =LET(s,PaymentsData!F:F,a,PaymentsData!D:D,SUMIF(s,"Paid",a))
B19: =LET( dates,PaymentsData!B2:B500, payees,PaymentsData!C2:C500, amounts,PaymentsData!D2:D500, dayPayments,FILTER(HSTACK(payees,amounts),DAY(dates)=14,""), IFERROR(INDEX(dayPayments,2,1)&" $"&TEXT(INDEX(dayPayments,2,2),"#,##0"),"") ) | C19: =LET( dates,PaymentsData!B2:B500, payees,PaymentsData!C2:C500, amounts,PaymentsData!D2:D500, dayPayments,FILTER(HSTACK(payees,amounts),DAY(dates)=15,""), IFERROR(INDEX(dayPayments,2,1)&" $"&TEXT(INDEX(dayPayments,2,2),"#,##0"),"") ) | D19: =LET( dates,PaymentsData!B2:B500, payees,PaymentsData!C2:C500, amounts,PaymentsData!D2:D500, dayPayments,FILTER(HSTACK(payees,amounts),DAY(dates)=16,""), IFERROR(INDEX(dayPayments,2,1)&" $"&TEXT(INDEX(dayPayments,2,2),"#,##0"),"") ) | E19: =LET( dates,PaymentsData!B2:B500, payees,PaymentsData!C2:C500, amounts,PaymentsData!D2:D500, dayPayments,FILTER(HSTACK(payees,amounts),DAY(dates)=17,""), IFERROR(INDEX(dayPayments,2,1)&" $"&TEXT(INDEX(dayPayments,2,2),"#,##0"),"") ) | F19: =LET( dates,PaymentsData!B2:B500, payees,PaymentsData!C2:C500, amounts,PaymentsData!D2:D500, dayPayments,FILTER(HSTACK(payees,amounts),DAY(dates)=18,""), IFERROR(INDEX(dayPayments,2,1)&" $"&TEXT(INDEX(dayPayments,2,2),"#,##0"),"") ) | G19: =LET( dates,PaymentsData!B2:B500, payees,PaymentsData!C2:C500, amounts,PaymentsData!D2:D500, dayPayments,FILTER(HSTACK(payees,amounts),DAY(dates)=19,""), IFERROR(INDEX(dayPayments,2,1)&" $"&TEXT(INDEX(dayPayments,2,2),"#,##0"),"") ) | H19: =LET( dates,PaymentsData!B2:B500, payees,PaymentsData!C2:C500, amounts,PaymentsData!D2:D500, dayPayments,FILTER(HSTACK(payees,amounts),DAY(dates)=20,""), IFERROR(INDEX(dayPayments,2,1)&" $"&TEXT(INDEX(dayPayments,2,2),"#,##0"),"") ) | J19: Overdue: | K19: =LET(s,PaymentsData!F:F,a,PaymentsData!D:D,SUMIF(s,"Overdue",a))
B20: =LET( dates,PaymentsData!B2:B500, payees,PaymentsData!C2:C500, amounts,PaymentsData!D2:D500, dayPayments,FILTER(HSTACK(payees,amounts),DAY(dates)=14,""), IFERROR(INDEX(dayPayments,3,1)&" $"&TEXT(INDEX(dayPayments,3,2),"#,##0"),"") ) | C20: =LET( dates,PaymentsData!B2:B500, payees,PaymentsData!C2:C500, amounts,PaymentsData!D2:D500, dayPayments,FILTER(HSTACK(payees,amounts),DAY(dates)=15,""), IFERROR(INDEX(dayPayments,3,1)&" $"&TEXT(INDEX(dayPayments,3,2),"#,##0"),"") ) | D20: =LET( dates,PaymentsData!B2:B500, payees,PaymentsData!C2:C500, amounts,PaymentsData!D2:D500, dayPayments,FILTER(HSTACK(payees,amounts),DAY(dates)=16,""), IFERROR(INDEX(dayPayments,3,1)&" $"&TEXT(INDEX(dayPayments,3,2),"#,##0"),"") ) | E20: =LET( dates,PaymentsData!B2:B500, payees,PaymentsData!C2:C500, amounts,PaymentsData!D2:D500, dayPayments,FILTER(HSTACK(payees,amounts),DAY(dates)=17,""), IFERROR(INDEX(dayPayments,3,1)&" $"&TEXT(INDEX(dayPayments,3,2),"#,##0"),"") ) | F20: =LET( dates,PaymentsData!B2:B500, payees,PaymentsData!C2:C500, amounts,PaymentsData!D2:D500, dayPayments,FILTER(HSTACK(payees,amounts),DAY(dates)=18,""), IFERROR(INDEX(dayPayments,3,1)&" $"&TEXT(INDEX(dayPayments,3,2),"#,##0"),"") ) | G20: =LET( dates,PaymentsData!B2:B500, payees,PaymentsData!C2:C500, amounts,PaymentsData!D2:D500, dayPayments,FILTER(HSTACK(payees,amounts),DAY(dates)=19,""), IFERROR(INDEX(dayPayments,3,1)&" $"&TEXT(INDEX(dayPayments,3,2),"#,##0"),"") ) | H20: =LET( dates,PaymentsData!B2:B500, payees,PaymentsData!C2:C500, amounts,PaymentsData!D2:D500, dayPayments,FILTER(HSTACK(payees,amounts),DAY(dates)=20,""), IFERROR(INDEX(dayPayments,3,1)&" $"&TEXT(INDEX(dayPayments,3,2),"#,##0"),"") )
B22: 21 | C22: 22 | D22: 23 | E22: 24 | F22: 25 | G22: 26 | H22: 27
B23: =LET( dates,PaymentsData!B2:B500, payees,PaymentsData!C2:C500, amounts,PaymentsData!D2:D500, dayPayments,FILTER(HSTACK(payees,amounts),DAY(dates)=21,""), IFERROR(INDEX(dayPayments,1,1)&" $"&TEXT(INDEX(dayPayments,1,2),"#,##0"),"") ) | C23: =LET( dates,PaymentsData!B2:B500, payees,PaymentsData!C2:C500, amounts,PaymentsData!D2:D500, dayPayments,FILTER(HSTACK(payees,amounts),DAY(dates)=22,""), IFERROR(INDEX(dayPayments,1,1)&" $"&TEXT(INDEX(dayPayments,1,2),"#,##0"),"") ) | D23: =LET( dates,PaymentsData!B2:B500, payees,PaymentsData!C2:C500, amounts,PaymentsData!D2:D500, dayPayments,FILTER(HSTACK(payees,amounts),DAY(dates)=23,""), IFERROR(INDEX(dayPayments,1,1)&" $"&TEXT(INDEX(dayPayments,1,2),"#,##0"),"") ) | E23: =LET( dates,PaymentsData!B2:B500, payees,PaymentsData!C2:C500, amounts,PaymentsData!D2:D500, dayPayments,FILTER(HSTACK(payees,amounts),DAY(dates)=24,""), IFERROR(INDEX(dayPayments,1,1)&" $"&TEXT(INDEX(dayPayments,1,2),"#,##0"),"") ) | F23: =LET( dates,PaymentsData!B2:B500, payees,PaymentsData!C2:C500, amounts,PaymentsData!D2:D500, dayPayments,FILTER(HSTACK(payees,amounts),DAY(dates)=25,""), IFERROR(INDEX(dayPayments,1,1)&" $"&TEXT(INDEX(dayPayments,1,2),"#,##0"),"") ) | G23: =LET( dates,PaymentsData!B2:B500, payees,PaymentsData!C2:C500, amounts,PaymentsData!D2:D500, dayPayments,FILTER(HSTACK(payees,amounts),DAY(dates)=26,""), IFERROR(INDEX(dayPayments,1,1)&" $"&TEXT(INDEX(dayPayments,1,2),"#,##0"),"") ) | H23: =LET( dates,PaymentsData!B2:B500, payees,PaymentsData!C2:C500, amounts,PaymentsData!D2:D500, dayPayments,FILTER(HSTACK(payees,amounts),DAY(dates)=27,""), IFERROR(INDEX(dayPayments,1,1)&" $"&TEXT(INDEX(dayPayments,1,2),"#,##0"),"") )
B24: =LET( dates,PaymentsData!B2:B500, payees,PaymentsData!C2:C500, amounts,PaymentsData!D2:D500, dayPayments,FILTER(HSTACK(payees,amounts),DAY(dates)=21,""), IFERROR(INDEX(dayPayments,2,1)&" $"&TEXT(INDEX(dayPayments,2,2),"#,##0"),"") ) | C24: =LET( dates,PaymentsData!B2:B500, payees,PaymentsData!C2:C500, amounts,PaymentsData!D2:D500, dayPayments,FILTER(HSTACK(payees,amounts),DAY(dates)=22,""), IFERROR(INDEX(dayPayments,2,1)&" $"&TEXT(INDEX(dayPayments,2,2),"#,##0"),"") ) | D24: =LET( dates,PaymentsData!B2:B500, payees,PaymentsData!C2:C500, amounts,PaymentsData!D2:D500, dayPayments,FILTER(HSTACK(payees,amounts),DAY(dates)=23,""), IFERROR(INDEX(dayPayments,2,1)&" $"&TEXT(INDEX(dayPayments,2,2),"#,##0"),"") ) | E24: =LET( dates,PaymentsData!B2:B500, payees,PaymentsData!C2:C500, amounts,PaymentsData!D2:D500, dayPayments,FILTER(HSTACK(payees,amounts),DAY(dates)=24,""), IFERROR(INDEX(dayPayments,2,1)&" $"&TEXT(INDEX(dayPayments,2,2),"#,##0"),"") ) | F24: =LET( dates,PaymentsData!B2:B500, payees,PaymentsData!C2:C500, amounts,PaymentsData!D2:D500, dayPayments,FILTER(HSTACK(payees,amounts),DAY(dates)=25,""), IFERROR(INDEX(dayPayments,2,1)&" $"&TEXT(INDEX(dayPayments,2,2),"#,##0"),"") ) | G24: =LET( dates,PaymentsData!B2:B500, payees,PaymentsData!C2:C500, amounts,PaymentsData!D2:D500, dayPayments,FILTER(HSTACK(payees,amounts),DAY(dates)=26,""), IFERROR(INDEX(dayPayments,2,1)&" $"&TEXT(INDEX(dayPayments,2,2),"#,##0"),"") ) | H24: =LET( dates,PaymentsData!B2:B500, payees,PaymentsData!C2:C500, amounts,PaymentsData!D2:D500, dayPayments,FILTER(HSTACK(payees,amounts),DAY(dates)=27,""), IFERROR(INDEX(dayPayments,2,1)&" $"&TEXT(INDEX(dayPayments,2,2),"#,##0"),"") )
B25: =LET( dates,PaymentsData!B2:B500, payees,PaymentsData!C2:C500, amounts,PaymentsData!D2:D500, dayPayments,FILTER(HSTACK(payees,amounts),DAY(dates)=21,""), IFERROR(INDEX(dayPayments,3,1)&" $"&TEXT(INDEX(dayPayments,3,2),"#,##0"),"") ) | C25: =LET( dates,PaymentsData!B2:B500, payees,PaymentsData!C2:C500, amounts,PaymentsData!D2:D500, dayPayments,FILTER(HSTACK(payees,amounts),DAY(dates)=22,""), IFERROR(INDEX(dayPayments,3,1)&" $"&TEXT(INDEX(dayPayments,3,2),"#,##0"),"") ) | D25: =LET( dates,PaymentsData!B2:B500, payees,PaymentsData!C2:C500, amounts,PaymentsData!D2:D500, dayPayments,FILTER(HSTACK(payees,amounts),DAY(dates)=23,""), IFERROR(INDEX(dayPayments,3,1)&" $"&TEXT(INDEX(dayPayments,3,2),"#,##0"),"") ) | E25: =LET( dates,PaymentsData!B2:B500, payees,PaymentsData!C2:C500, amounts,PaymentsData!D2:D500, dayPayments,FILTER(HSTACK(payees,amounts),DAY(dates)=24,""), IFERROR(INDEX(dayPayments,3,1)&" $"&TEXT(INDEX(dayPayments,3,2),"#,##0"),"") ) | F25: =LET( dates,PaymentsData!B2:B500, payees,PaymentsData!C2:C500, amounts,PaymentsData!D2:D500, dayPayments,FILTER(HSTACK(payees,amounts),DAY(dates)=25,""), IFERROR(INDEX(dayPayments,3,1)&" $"&TEXT(INDEX(dayPayments,3,2),"#,##0"),"") ) | G25: =LET( dates,PaymentsData!B2:B500, payees,PaymentsData!C2:C500, amounts,PaymentsData!D2:D500, dayPayments,FILTER(HSTACK(payees,amounts),DAY(dates)=26,""), IFERROR(INDEX(dayPayments,3,1)&" $"&TEXT(INDEX(dayPayments,3,2),"#,##0"),"") ) | H25: =LET( dates,PaymentsData!B2:B500, payees,PaymentsData!C2:C500, amounts,PaymentsData!D2:D500, dayPayments,FILTER(HSTACK(payees,amounts),DAY(dates)=27,""), IFERROR(INDEX(dayPayments,3,1)&" $"&TEXT(INDEX(dayPayments,3,2),"#,##0"),"") )
B27: 28 | C27: 29 | D27: 30 | E27: 31
B28: =LET( dates,PaymentsData!B2:B500, payees,PaymentsData!C2:C500, amounts,PaymentsData!D2:D500, dayPayments,FILTER(HSTACK(payees,amounts),DAY(dates)=28,""), IFERROR(INDEX(dayPayments,1,1)&" $"&TEXT(INDEX(dayPayments,1,2),"#,##0"),"") ) | C28: =LET( dates,PaymentsData!B2:B500, payees,PaymentsData!C2:C500, amounts,PaymentsData!D2:D500, dayPayments,FILTER(HSTACK(payees,amounts),DAY(dates)=29,""), IFERROR(INDEX(dayPayments,1,1)&" $"&TEXT(INDEX(dayPayments,1,2),"#,##0"),"") ) | D28: =LET( dates,PaymentsData!B2:B500, payees,PaymentsData!C2:C500, amounts,PaymentsData!D2:D500, dayPayments,FILTER(HSTACK(payees,amounts),DAY(dates)=30,""), IFERROR(INDEX(dayPayments,1,1)&" $"&TEXT(INDEX(dayPayments,1,2),"#,##0"),"") ) | E28: =LET( dates,PaymentsData!B2:B500, payees,PaymentsData!C2:C500, amounts,PaymentsData!D2:D500, dayPayments,FILTER(HSTACK(payees,amounts),DAY(dates)=31,""), IFERROR(INDEX(dayPayments,1,1)&" $"&TEXT(INDEX(dayPayments,1,2),"#,##0"),"") )
B29: =LET( dates,PaymentsData!B2:B500, payees,PaymentsData!C2:C500, amounts,PaymentsData!D2:D500, dayPayments,FILTER(HSTACK(payees,amounts),DAY(dates)=28,""), IFERROR(INDEX(dayPayments,2,1)&" $"&TEXT(INDEX(dayPayments,2,2),"#,##0"),"") ) | C29: =LET( dates,PaymentsData!B2:B500, payees,PaymentsData!C2:C500, amounts,PaymentsData!D2:D500, dayPayments,FILTER(HSTACK(payees,amounts),DAY(dates)=29,""), IFERROR(INDEX(dayPayments,2,1)&" $"&TEXT(INDEX(dayPayments,2,2),"#,##0"),"") ) | D29: =LET( dates,PaymentsData!B2:B500, payees,PaymentsData!C2:C500, amounts,PaymentsData!D2:D500, dayPayments,FILTER(HSTACK(payees,amounts),DAY(dates)=30,""), IFERROR(INDEX(dayPayments,2,1)&" $"&TEXT(INDEX(dayPayments,2,2),"#,##0"),"") ) | E29: =LET( dates,PaymentsData!B2:B500, payees,PaymentsData!C2:C500, amounts,PaymentsData!D2:D500, dayPayments,FILTER(HSTACK(payees,amounts),DAY(dates)=31,""), IFERROR(INDEX(dayPayments,2,1)&" $"&TEXT(INDEX(dayPayments,2,2),"#,##0"),"") )
B30: =LET( dates,PaymentsData!B2:B500, payees,PaymentsData!C2:C500, amounts,PaymentsData!D2:D500, dayPayments,FILTER(HSTACK(payees,amounts),DAY(dates)=28,""), IFERROR(INDEX(dayPayments,3,1)&" $"&TEXT(INDEX(dayPayments,3,2),"#,##0"),"") ) | C30: =LET( dates,PaymentsData!B2:B500, payees,PaymentsData!C2:C500, amounts,PaymentsData!D2:D500, dayPayments,FILTER(HSTACK(payees,amounts),DAY(dates)=29,""), IFERROR(INDEX(dayPayments,3,1)&" $"&TEXT(INDEX(dayPayments,3,2),"#,##0"),"") ) | D30: =LET( dates,PaymentsData!B2:B500, payees,PaymentsData!C2:C500, amounts,PaymentsData!D2:D500, dayPayments,FILTER(HSTACK(payees,amounts),DAY(dates)=30,""), IFERROR(INDEX(dayPayments,3,1)&" $"&TEXT(INDEX(dayPayments,3,2),"#,##0"),"") ) | E30: =LET( dates,PaymentsData!B2:B500, payees,PaymentsData!C2:C500, amounts,PaymentsData!D2:D500, dayPayments,FILTER(HSTACK(payees,amounts),DAY(dates)=31,""), IFERROR(INDEX(dayPayments,3,1)&" $"&TEXT(INDEX(dayPayments,3,2),"#,##0"),"") )

Sheet TimeDeposits
B2: Time Deposit Manager
B3: Track and manage your term deposits, CDs, and fixed-income investments
B5: Total Deposits | D5: Average Rate | F5: Expected Interest | H5: Maturing (30 days)
B6: =LET(status,DepositsData!G:G,principal,DepositsData!D:D,SUMIF(status,"Active",principal)) | D6: =LET(status,DepositsData!G:G,rates,DepositsData!E:E,AVERAGEIF(status,"Active",rates)) | F6: =LET(status,DepositsData!G:G,interest,DepositsData!H:H,SUMIF(status,"Active",interest)) | H6: =LET( maturity,DepositsData!F2:F100, principal,DepositsData!D2:D100, status,DepositsData!G2:G100, filtered,FILTER(principal,(maturity>=TODAY())*(maturity<=TODAY()+30)*(status="Active"),0), SUM(filtered) )
B9: Active Time Deposits
B10: ID | C10: Bank/Institution | D10: Principal | E10: Rate | F10: Start Date | G10: Maturity | H10: Days Left | I10: Interest | J10: Status
B11: =DepositsData!A2 | C11: =DepositsData!B2 | D11: =DepositsData!D2 | E11: =DepositsData!E2 | F11: =DepositsData!C2 | G11: =DepositsData!F2 | H11: =LET(maturity,DepositsData!F2,IF(maturity="","",MAX(0,maturity-TODAY()))) | I11: =DepositsData!H2 | J11: =DepositsData!G2
B12: =DepositsData!A3 | C12: =DepositsData!B3 | D12: =DepositsData!D3 | E12: =DepositsData!E3 | F12: =DepositsData!C3 | G12: =DepositsData!F3 | H12: =LET(maturity,DepositsData!F3,IF(maturity="","",MAX(0,maturity-TODAY()))) | I12: =DepositsData!H3 | J12: =DepositsData!G3
B13: =DepositsData!A4 | C13: =DepositsData!B4 | D13: =DepositsData!D4 | E13: =DepositsData!E4 | F13: =DepositsData!C4 | G13: =DepositsData!F4 | H13: =LET(maturity,DepositsData!F4,IF(maturity="","",MAX(0,maturity-TODAY()))) | I13: =DepositsData!H4 | J13: =DepositsData!G4
B14: =DepositsData!A5 | C14: =DepositsData!B5 | D14: =DepositsData!D5 | E14: =DepositsData!E5 | F14: =DepositsData!C5 | G14: =DepositsData!F5 | H14: =LET(maturity,DepositsData!F5,IF(maturity="","",MAX(0,maturity-TODAY()))) | I14: =DepositsData!H5 | J14: =DepositsData!G5
B15: =DepositsData!A6 | C15: =DepositsData!B6 | D15: =DepositsData!D6 | E15: =DepositsData!E6 | F15: =DepositsData!C6 | G15: =DepositsData!F6 | H15: =LET(maturity,DepositsData!F6,IF(maturity="","",MAX(0,maturity-TODAY()))) | I15: =DepositsData!H6 | J15: =DepositsData!G6
B16: =DepositsData!A7 | C16: =DepositsData!B7 | D16: =DepositsData!D7 | E16: =DepositsData!E7 | F16: =DepositsData!C7 | G16: =DepositsData!F7 | H16: =LET(maturity,DepositsData!F7,IF(maturity="","",MAX(0,maturity-TODAY()))) | I16: =DepositsData!H7 | J16: =DepositsData!G7
B17: =DepositsData!A8 | C17: =DepositsData!B8 | D17: =DepositsData!D8 | E17: =DepositsData!E8 | F17: =DepositsData!C8 | G17: =DepositsData!F8 | H17: =LET(maturity,DepositsData!F8,IF(maturity="","",MAX(0,maturity-TODAY()))) | I17: =DepositsData!H8 | J17: =DepositsData!G8
B18: =DepositsData!A9 | C18: =DepositsData!B9 | D18: =DepositsData!D9 | E18: =DepositsData!E9 | F18: =DepositsData!C9 | G18: =DepositsData!F9 | H18: =LET(maturity,DepositsData!F9,IF(maturity="","",MAX(0,maturity-TODAY()))) | I18: =DepositsData!H9 | J18: =DepositsData!G9
B19: =DepositsData!A10 | C19: =DepositsData!B10 | D19: =DepositsData!D10 | E19: =DepositsData!E10 | F19: =DepositsData!C10 | G19: =DepositsData!F10 | H19: =LET(maturity,DepositsData!F10,IF(maturity="","",MAX(0,maturity-TODAY()))) | I19: =DepositsData!H10 | J19: =DepositsData!G10
B20: =DepositsData!A11 | C20: =DepositsData!B11 | D20: =DepositsData!D11 | E20: =DepositsData!E11 | F20: =DepositsData!C11 | G20: =DepositsData!F11 | H20: =LET(maturity,DepositsData!F11,IF(maturity="","",MAX(0,maturity-TODAY()))) | I20: =DepositsData!H11 | J20: =DepositsData!G11
B21: =DepositsData!A12 | C21: =DepositsData!B12 | D21: =DepositsData!D12 | E21: =DepositsData!E12 | F21: =DepositsData!C12 | G21: =DepositsData!F12 | H21: =LET(maturity,DepositsData!F12,IF(maturity="","",MAX(0,maturity-TODAY()))) | I21: =DepositsData!H12 | J21: =DepositsData!G12
B22: =DepositsData!A13 | C22: =DepositsData!B13 | D22: =DepositsData!D13 | E22: =DepositsData!E13 | F22: =DepositsData!C13 | G22: =DepositsData!F13 | H22: =LET(maturity,DepositsData!F13,IF(maturity="","",MAX(0,maturity-TODAY()))) | I22: =DepositsData!H13 | J22: =DepositsData!G13
... B25: =DepositsData!A16 | C25: =DepositsData!B16 | D25: =DepositsData!D16 | E25: =DepositsData!E16 | F25: =DepositsData!C16 | G25: =DepositsData!F16 | H25: =LET(maturity,DepositsData!F16,IF(maturity="","",MAX(0,maturity-TODAY()))) | I25: =DepositsData!H16 | J25: =DepositsData!G16
B28: Maturity Ladder
B29: Period | C29: Count | D29: Amount | E29: % of Total
B30: 0-30 Days | C30: =LET( maturity,DepositsData!F2:F100, status,DepositsData!G2:G100, daysToMaturity,maturity-TODAY(), ROWS(FILTER(maturity,(daysToMaturity>=0)*(daysToMaturity<=30)*(status="Active"),{})) ) | D30: =LET( maturity,DepositsData!F2:F100, principal,DepositsData!D2:D100, status,DepositsData!G2:G100, daysToMaturity,maturity-TODAY(), filtered,FILTER(principal,(daysToMaturity>=0)*(daysToMaturity<=30)*(status="Active"),0), SUM(filtered) ) | E30: =LET(amt,D30,total,SUMIF(DepositsData!G:G,"Active",DepositsData!D:D),IFERROR(amt/total,0))
B31: 31-60 Days | C31: =LET( maturity,DepositsData!F2:F100, status,DepositsData!G2:G100, daysToMaturity,maturity-TODAY(), ROWS(FILTER(maturity,(daysToMaturity>=31)*(daysToMaturity<=60)*(status="Active"),{})) ) | D31: =LET( maturity,DepositsData!F2:F100, principal,DepositsData!D2:D100, status,DepositsData!G2:G100, daysToMaturity,maturity-TODAY(), filtered,FILTER(principal,(daysToMaturity>=31)*(daysToMaturity<=60)*(status="Active"),0), SUM(filtered) ) | E31: =LET(amt,D31,total,SUMIF(DepositsData!G:G,"Active",DepositsData!D:D),IFERROR(amt/total,0))
B32: 61-90 Days | C32: =LET( maturity,DepositsData!F2:F100, status,DepositsData!G2:G100, daysToMaturity,maturity-TODAY(), ROWS(FILTER(maturity,(daysToMaturity>=61)*(daysToMaturity<=90)*(status="Active"),{})) ) | D32: =LET( maturity,DepositsData!F2:F100, principal,DepositsData!D2:D100, status,DepositsData!G2:G100, daysToMaturity,maturity-TODAY(), filtered,FILTER(principal,(daysToMaturity>=61)*(daysToMaturity<=90)*(status="Active"),0), SUM(filtered) ) | E32: =LET(amt,D32,total,SUMIF(DepositsData!G:G,"Active",DepositsData!D:D),IFERROR(amt/total,0))
B33: 91-180 Days | C33: =LET( maturity,DepositsData!F2:F100, status,DepositsData!G2:G100, daysToMaturity,maturity-TODAY(), ROWS(FILTER(maturity,(daysToMaturity>=91)*(daysToMaturity<=180)*(status="Active"),{})) ) | D33: =LET( maturity,DepositsData!F2:F100, principal,DepositsData!D2:D100, status,DepositsData!G2:G100, daysToMaturity,maturity-TODAY(), filtered,FILTER(principal,(daysToMaturity>=91)*(daysToMaturity<=180)*(status="Active"),0), SUM(filtered) ) | E33: =LET(amt,D33,total,SUMIF(DepositsData!G:G,"Active",DepositsData!D:D),IFERROR(amt/total,0))
B34: 180+ Days | C34: =LET( maturity,DepositsData!F2:F100, status,DepositsData!G2:G100, daysToMaturity,maturity-TODAY(), ROWS(FILTER(maturity,(daysToMaturity>=181)*(daysToMaturity<=9999)*(status="Active"),{})) ) | D34: =LET( maturity,DepositsData!F2:F100, principal,DepositsData!D2:D100, status,DepositsData!G2:G100, daysToMaturity,maturity-TODAY(), filtered,FILTER(principal,(daysToMaturity>=181)*(daysToMaturity<=9999)*(status="Active"),0), SUM(filtered) ) | E34: =LET(amt,D34,total,SUMIF(DepositsData!G:G,"Active",DepositsData!D:D),IFERROR(amt/total,0))

Sheet CashFlowPositions
B2: Cash Flow Positions
B3: Comprehensive view of cash inflows, outflows, and positions
B5: Position Summary
B6: Period | C6: Start Balance | D6: Inflows | E6: Outflows | F6: Net Flow | G6: End Balance | H6: Change %
B7: Today | C7: =CashTransactions!J2 | D7: =LET( txDates,CashTransactions!B2:B500, txAmounts,CashTransactions!D2:D500, depMaturity,DepositsData!F2:F100, depPrincipal,DepositsData!D2:D100, depInterest,DepositsData!H2:H100, depStatus,DepositsData!G2:G100, startDt,TODAY(), endDt,TODAY(), cashInflows,SUM(FILTER(txAmounts,(txDates>=startDt)*(txDates<=endDt)*(txAmounts>0),0)), depositInflows,SUM(FILTER(depPrincipal+depInterest,(depMaturity>=startDt)*(depMaturity<=endDt)*(depStatus="Active"),0)), cashInflows+depositInflows ) | E7: =LET( payDates,PaymentsData!B2:B500, payAmounts,PaymentsData!D2:D500, payStatus,PaymentsData!F2:F500, txDates,CashTransactions!B2:B500, txAmounts,CashTransactions!D2:D500, startDt,TODAY(), endDt,TODAY(), paymentOut,SUM(FILTER(payAmounts,(payDates>=startDt)*(payDates<=endDt)*(payStatus<>"Cancelled"),0)), cashOut,ABS(SUM(FILTER(txAmounts,(txDates>=startDt)*(txDates<=endDt)*(txAmounts<0),0))), paymentOut+cashOut ) | F7: =D7-E7 | G7: =C7+F7 | H7: =LET(net,F7,start,C7,IFERROR(net/start,0))
B8: This Week | C8: =CashTransactions!J2 | D8: =LET( txDates,CashTransactions!B2:B500, txAmounts,CashTransactions!D2:D500, depMaturity,DepositsData!F2:F100, depPrincipal,DepositsData!D2:D100, depInterest,DepositsData!H2:H100, depStatus,DepositsData!G2:G100, startDt,TODAY()-WEEKDAY(TODAY(),2)+1, endDt,TODAY()-WEEKDAY(TODAY(),2)+7, cashInflows,SUM(FILTER(txAmounts,(txDates>=startDt)*(txDates<=endDt)*(txAmounts>0),0)), depositInflows,SUM(FILTER(depPrincipal+depInterest,(depMaturity>=startDt)*(depMaturity<=endDt)*(depStatus="Active"),0)), cashInflows+depositInflows ) | E8: =LET( payDates,PaymentsData!B2:B500, payAmounts,PaymentsData!D2:D500, payStatus,PaymentsData!F2:F500, txDates,CashTransactions!B2:B500, txAmounts,CashTransactions!D2:D500, startDt,TODAY()-WEEKDAY(TODAY(),2)+1, endDt,TODAY()-WEEKDAY(TODAY(),2)+7, paymentOut,SUM(FILTER(payAmounts,(payDates>=startDt)*(payDates<=endDt)*(payStatus<>"Cancelled"),0)), cashOut,ABS(SUM(FILTER(txAmounts,(txDates>=startDt)*(txDates<=endDt)*(txAmounts<0),0))), paymentOut+cashOut ) | F8: =D8-E8 | G8: =C8+F8 | H8: =LET(net,F8,start,C8,IFERROR(net/start,0))
B9: This Month | C9: =CashTransactions!J2 | D9: =LET( txDates,CashTransactions!B2:B500, txAmounts,CashTransactions!D2:D500, depMaturity,DepositsData!F2:F100, depPrincipal,DepositsData!D2:D100, depInterest,DepositsData!H2:H100, depStatus,DepositsData!G2:G100, startDt,DATE(YEAR(TODAY()),MONTH(TODAY()),1), endDt,EOMONTH(TODAY(),0), cashInflows,SUM(FILTER(txAmounts,(txDates>=startDt)*(txDates<=endDt)*(txAmounts>0),0)), depositInflows,SUM(FILTER(depPrincipal+depInterest,(depMaturity>=startDt)*(depMaturity<=endDt)*(depStatus="Active"),0)), cashInflows+depositInflows ) | E9: =LET( payDates,PaymentsData!B2:B500, payAmounts,PaymentsData!D2:D500, payStatus,PaymentsData!F2:F500, txDates,CashTransactions!B2:B500, txAmounts,CashTransactions!D2:D500, startDt,DATE(YEAR(TODAY()),MONTH(TODAY()),1), endDt,EOMONTH(TODAY(),0), paymentOut,SUM(FILTER(payAmounts,(payDates>=startDt)*(payDates<=endDt)*(payStatus<>"Cancelled"),0)), cashOut,ABS(SUM(FILTER(txAmounts,(txDates>=startDt)*(txDates<=endDt)*(txAmounts<0),0))), paymentOut+cashOut ) | F9: =D9-E9 | G9: =C9+F9 | H9: =LET(net,F9,start,C9,IFERROR(net/start,0))
B10: Next 30 Days | C10: =CashTransactions!J2 | D10: =LET( txDates,CashTransactions!B2:B500, txAmounts,CashTransactions!D2:D500, depMaturity,DepositsData!F2:F100, depPrincipal,DepositsData!D2:D100, depInterest,DepositsData!H2:H100, depStatus,DepositsData!G2:G100, startDt,TODAY(), endDt,TODAY()+30, cashInflows,SUM(FILTER(txAmounts,(txDates>=startDt)*(txDates<=endDt)*(txAmounts>0),0)), depositInflows,SUM(FILTER(depPrincipal+depInterest,(depMaturity>=startDt)*(depMaturity<=endDt)*(depStatus="Active"),0)), cashInflows+depositInflows ) | E10: =LET( payDates,PaymentsData!B2:B500, payAmounts,PaymentsData!D2:D500, payStatus,PaymentsData!F2:F500, txDates,CashTransactions!B2:B500, txAmounts,CashTransactions!D2:D500, startDt,TODAY(), endDt,TODAY()+30, paymentOut,SUM(FILTER(payAmounts,(payDates>=startDt)*(payDates<=endDt)*(payStatus<>"Cancelled"),0)), cashOut,ABS(SUM(FILTER(txAmounts,(txDates>=startDt)*(txDates<=endDt)*(txAmounts<0),0))), paymentOut+cashOut ) | F10: =D10-E10 | G10: =C10+F10 | H10: =LET(net,F10,start,C10,IFERROR(net/start,0))
B11: Next 60 Days | C11: =CashTransactions!J2 | D11: =LET( txDates,CashTransactions!B2:B500, txAmounts,CashTransactions!D2:D500, depMaturity,DepositsData!F2:F100, depPrincipal,DepositsData!D2:D100, depInterest,DepositsData!H2:H100, depStatus,DepositsData!G2:G100, startDt,TODAY(), endDt,TODAY()+60, cashInflows,SUM(FILTER(txAmounts,(txDates>=startDt)*(txDates<=endDt)*(txAmounts>0),0)), depositInflows,SUM(FILTER(depPrincipal+depInterest,(depMaturity>=startDt)*(depMaturity<=endDt)*(depStatus="Active"),0)), cashInflows+depositInflows ) | E11: =LET( payDates,PaymentsData!B2:B500, payAmounts,PaymentsData!D2:D500, payStatus,PaymentsData!F2:F500, txDates,CashTransactions!B2:B500, txAmounts,CashTransactions!D2:D500, startDt,TODAY(), endDt,TODAY()+60, paymentOut,SUM(FILTER(payAmounts,(payDates>=startDt)*(payDates<=endDt)*(payStatus<>"Cancelled"),0)), cashOut,ABS(SUM(FILTER(txAmounts,(txDates>=startDt)*(txDates<=endDt)*(txAmounts<0),0))), paymentOut+cashOut ) | F11: =D11-E11 | G11: =C11+F11 | H11: =LET(net,F11,start,C11,IFERROR(net/start,0))
B12: Next 90 Days | C12: =CashTransactions!J2 | D12: =LET( txDates,CashTransactions!B2:B500, txAmounts,CashTransactions!D2:D500, depMaturity,DepositsData!F2:F100, depPrincipal,DepositsData!D2:D100, depInterest,DepositsData!H2:H100, depStatus,DepositsData!G2:G100, startDt,TODAY(), endDt,TODAY()+90, cashInflows,SUM(FILTER(txAmounts,(txDates>=startDt)*(txDates<=endDt)*(txAmounts>0),0)), depositInflows,SUM(FILTER(depPrincipal+depInterest,(depMaturity>=startDt)*(depMaturity<=endDt)*(depStatus="Active"),0)), cashInflows+depositInflows ) | E12: =LET( payDates,PaymentsData!B2:B500, payAmounts,PaymentsData!D2:D500, payStatus,PaymentsData!F2:F500, txDates,CashTransactions!B2:B500, txAmounts,CashTransactions!D2:D500, startDt,TODAY(), endDt,TODAY()+90, paymentOut,SUM(FILTER(payAmounts,(payDates>=startDt)*(payDates<=endDt)*(payStatus<>"Cancelled"),0)), cashOut,ABS(SUM(FILTER(txAmounts,(txDates>=startDt)*(txDates<=endDt)*(txAmounts<0),0))), paymentOut+cashOut ) | F12: =D12-E12 | G12: =C12+F12 | H12: =LET(net,F12,start,C12,IFERROR(net/start,0))
B14: Daily Positions (Next 14 Days)
B15: Date | C15: Day | D15: Inflows | E15: Outflows | F15: Net | G15: Running Balance
B16: =TODAY()+0 | C16: =LET(dt,B16,TEXT(dt,"dddd")) | D16: =LET( dt,B16, txDates,CashTransactions!B:B, txAmounts,CashTransactions!D:D, depMaturity,DepositsData!F:F, depPrincipal,DepositsData!D:D, depInterest,DepositsData!H:H, depStatus,DepositsData!G:G, cashIn,SUMIF(txDates,dt,txAmounts), depIn,SUMPRODUCT((depMaturity=dt)*(depStatus="Active")*(depPrincipal+depInterest)), MAX(0,cashIn)+depIn ) | E16: =LET( dt,B16, payDates,PaymentsData!B:B, payAmounts,PaymentsData!D:D, payStatus,PaymentsData!F:F, txDates,CashTransactions!B:B, txAmounts,CashTransactions!D:D, payments,SUMPRODUCT((payDates=dt)*(payStatus<>"Cancelled")*payAmounts), cashOut,ABS(MIN(0,SUMIF(txDates,dt,txAmounts))), payments+cashOut ) | F16: =D16-E16 | G16: =CashTransactions!J2+F16
B17: =TODAY()+1 | C17: =LET(dt,B17,TEXT(dt,"dddd")) | D17: =LET( dt,B17, txDates,CashTransactions!B:B, txAmounts,CashTransactions!D:D, depMaturity,DepositsData!F:F, depPrincipal,DepositsData!D:D, depInterest,DepositsData!H:H, depStatus,DepositsData!G:G, cashIn,SUMIF(txDates,dt,txAmounts), depIn,SUMPRODUCT((depMaturity=dt)*(depStatus="Active")*(depPrincipal+depInterest)), MAX(0,cashIn)+depIn ) | E17: =LET( dt,B17, payDates,PaymentsData!B:B, payAmounts,PaymentsData!D:D, payStatus,PaymentsData!F:F, txDates,CashTransactions!B:B, txAmounts,CashTransactions!D:D, payments,SUMPRODUCT((payDates=dt)*(payStatus<>"Cancelled")*payAmounts), cashOut,ABS(MIN(0,SUMIF(txDates,dt,txAmounts))), payments+cashOut ) | F17: =D17-E17 | G17: =G16+F17
B18: =TODAY()+2 | C18: =LET(dt,B18,TEXT(dt,"dddd")) | D18: =LET( dt,B18, txDates,CashTransactions!B:B, txAmounts,CashTransactions!D:D, depMaturity,DepositsData!F:F, depPrincipal,DepositsData!D:D, depInterest,DepositsData!H:H, depStatus,DepositsData!G:G, cashIn,SUMIF(txDates,dt,txAmounts), depIn,SUMPRODUCT((depMaturity=dt)*(depStatus="Active")*(depPrincipal+depInterest)), MAX(0,cashIn)+depIn ) | E18: =LET( dt,B18, payDates,PaymentsData!B:B, payAmounts,PaymentsData!D:D, payStatus,PaymentsData!F:F, txDates,CashTransactions!B:B, txAmounts,CashTransactions!D:D, payments,SUMPRODUCT((payDates=dt)*(payStatus<>"Cancelled")*payAmounts), cashOut,ABS(MIN(0,SUMIF(txDates,dt,txAmounts))), payments+cashOut ) | F18: =D18-E18 | G18: =G17+F18
B19: =TODAY()+3 | C19: =LET(dt,B19,TEXT(dt,"dddd")) | D19: =LET( dt,B19, txDates,CashTransactions!B:B, txAmounts,CashTransactions!D:D, depMaturity,DepositsData!F:F, depPrincipal,DepositsData!D:D, depInterest,DepositsData!H:H, depStatus,DepositsData!G:G, cashIn,SUMIF(txDates,dt,txAmounts), depIn,SUMPRODUCT((depMaturity=dt)*(depStatus="Active")*(depPrincipal+depInterest)), MAX(0,cashIn)+depIn ) | E19: =LET( dt,B19, payDates,PaymentsData!B:B, payAmounts,PaymentsData!D:D, payStatus,PaymentsData!F:F, txDates,CashTransactions!B:B, txAmounts,CashTransactions!D:D, payments,SUMPRODUCT((payDates=dt)*(payStatus<>"Cancelled")*payAmounts), cashOut,ABS(MIN(0,SUMIF(txDates,dt,txAmounts))), payments+cashOut ) | F19: =D19-E19 | G19: =G18+F19
B20: =TODAY()+4 | C20: =LET(dt,B20,TEXT(dt,"dddd")) | D20: =LET( dt,B20, txDates,CashTransactions!B:B, txAmounts,CashTransactions!D:D, depMaturity,DepositsData!F:F, depPrincipal,DepositsData!D:D, depInterest,DepositsData!H:H, depStatus,DepositsData!G:G, cashIn,SUMIF(txDates,dt,txAmounts), depIn,SUMPRODUCT((depMaturity=dt)*(depStatus="Active")*(depPrincipal+depInterest)), MAX(0,cashIn)+depIn ) | E20: =LET( dt,B20, payDates,PaymentsData!B:B, payAmounts,PaymentsData!D:D, payStatus,PaymentsData!F:F, txDates,CashTransactions!B:B, txAmounts,CashTransactions!D:D, payments,SUMPRODUCT((payDates=dt)*(payStatus<>"Cancelled")*payAmounts), cashOut,ABS(MIN(0,SUMIF(txDates,dt,txAmounts))), payments+cashOut ) | F20: =D20-E20 | G20: =G19+F20
B21: =TODAY()+5 | C21: =LET(dt,B21,TEXT(dt,"dddd")) | D21: =LET( dt,B21, txDates,CashTransactions!B:B, txAmounts,CashTransactions!D:D, depMaturity,DepositsData!F:F, depPrincipal,DepositsData!D:D, depInterest,DepositsData!H:H, depStatus,DepositsData!G:G, cashIn,SUMIF(txDates,dt,txAmounts), depIn,SUMPRODUCT((depMaturity=dt)*(depStatus="Active")*(depPrincipal+depInterest)), MAX(0,cashIn)+depIn ) | E21: =LET( dt,B21, payDates,PaymentsData!B:B, payAmounts,PaymentsData!D:D, payStatus,PaymentsData!F:F, txDates,CashTransactions!B:B, txAmounts,CashTransactions!D:D, payments,SUMPRODUCT((payDates=dt)*(payStatus<>"Cancelled")*payAmounts), cashOut,ABS(MIN(0,SUMIF(txDates,dt,txAmounts))), payments+cashOut ) | F21: =D21-E21 | G21: =G20+F21
B22: =TODAY()+6 | C22: =LET(dt,B22,TEXT(dt,"dddd")) | D22: =LET( dt,B22, txDates,CashTransactions!B:B, txAmounts,CashTransactions!D:D, depMaturity,DepositsData!F:F, depPrincipal,DepositsData!D:D, depInterest,DepositsData!H:H, depStatus,DepositsData!G:G, cashIn,SUMIF(txDates,dt,txAmounts), depIn,SUMPRODUCT((depMaturity=dt)*(depStatus="Active")*(depPrincipal+depInterest)), MAX(0,cashIn)+depIn ) | E22: =LET( dt,B22, payDates,PaymentsData!B:B, payAmounts,PaymentsData!D:D, payStatus,PaymentsData!F:F, txDates,CashTransactions!B:B, txAmounts,CashTransactions!D:D, payments,SUMPRODUCT((payDates=dt)*(payStatus<>"Cancelled")*payAmounts), cashOut,ABS(MIN(0,SUMIF(txDates,dt,txAmounts))), payments+cashOut ) | F22: =D22-E22 | G22: =G21+F22
B23: =TODAY()+7 | C23: =LET(dt,B23,TEXT(dt,"dddd")) | D23: =LET( dt,B23, txDates,CashTransactions!B:B, txAmounts,CashTransactions!D:D, depMaturity,DepositsData!F:F, depPrincipal,DepositsData!D:D, depInterest,DepositsData!H:H, depStatus,DepositsData!G:G, cashIn,SUMIF(txDates,dt,txAmounts), depIn,SUMPRODUCT((depMaturity=dt)*(depStatus="Active")*(depPrincipal+depInterest)), MAX(0,cashIn)+depIn ) | E23: =LET( dt,B23, payDates,PaymentsData!B:B, payAmounts,PaymentsData!D:D, payStatus,PaymentsData!F:F, txDates,CashTransactions!B:B, txAmounts,CashTransactions!D:D, payments,SUMPRODUCT((payDates=dt)*(payStatus<>"Cancelled")*payAmounts), cashOut,ABS(MIN(0,SUMIF(txDates,dt,txAmounts))), payments+cashOut ) | F23: =D23-E23 | G23: =G22+F23
B24: =TODAY()+8 | C24: =LET(dt,B24,TEXT(dt,"dddd")) | D24: =LET( dt,B24, txDates,CashTransactions!B:B, txAmounts,CashTransactions!D:D, depMaturity,DepositsData!F:F, depPrincipal,DepositsData!D:D, depInterest,DepositsData!H:H, depStatus,DepositsData!G:G, cashIn,SUMIF(txDates,dt,txAmounts), depIn,SUMPRODUCT((depMaturity=dt)*(depStatus="Active")*(depPrincipal+depInterest)), MAX(0,cashIn)+depIn ) | E24: =LET( dt,B24, payDates,PaymentsData!B:B, payAmounts,PaymentsData!D:D, payStatus,PaymentsData!F:F, txDates,CashTransactions!B:B, txAmounts,CashTransactions!D:D, payments,SUMPRODUCT((payDates=dt)*(payStatus<>"Cancelled")*payAmounts), cashOut,ABS(MIN(0,SUMIF(txDates,dt,txAmounts))), payments+cashOut ) | F24: =D24-E24 | G24: =G23+F24
B25: =TODAY()+9 | C25: =LET(dt,B25,TEXT(dt,"dddd")) | D25: =LET( dt,B25, txDates,CashTransactions!B:B, txAmounts,CashTransactions!D:D, depMaturity,DepositsData!F:F, depPrincipal,DepositsData!D:D, depInterest,DepositsData!H:H, depStatus,DepositsData!G:G, cashIn,SUMIF(txDates,dt,txAmounts), depIn,SUMPRODUCT((depMaturity=dt)*(depStatus="Active")*(depPrincipal+depInterest)), MAX(0,cashIn)+depIn ) | E25: =LET( dt,B25, payDates,PaymentsData!B:B, payAmounts,PaymentsData!D:D, payStatus,PaymentsData!F:F, txDates,CashTransactions!B:B, txAmounts,CashTransactions!D:D, payments,SUMPRODUCT((payDates=dt)*(payStatus<>"Cancelled")*payAmounts), cashOut,ABS(MIN(0,SUMIF(txDates,dt,txAmounts))), payments+cashOut ) | F25: =D25-E25 | G25: =G24+F25
B26: =TODAY()+10 | C26: =LET(dt,B26,TEXT(dt,"dddd")) | D26: =LET( dt,B26, txDates,CashTransactions!B:B, txAmounts,CashTransactions!D:D, depMaturity,DepositsData!F:F, depPrincipal,DepositsData!D:D, depInterest,DepositsData!H:H, depStatus,DepositsData!G:G, cashIn,SUMIF(txDates,dt,txAmounts), depIn,SUMPRODUCT((depMaturity=dt)*(depStatus="Active")*(depPrincipal+depInterest)), MAX(0,cashIn)+depIn ) | E26: =LET( dt,B26, payDates,PaymentsData!B:B, payAmounts,PaymentsData!D:D, payStatus,PaymentsData!F:F, txDates,CashTransactions!B:B, txAmounts,CashTransactions!D:D, payments,SUMPRODUCT((payDates=dt)*(payStatus<>"Cancelled")*payAmounts), cashOut,ABS(MIN(0,SUMIF(txDates,dt,txAmounts))), payments+cashOut ) | F26: =D26-E26 | G26: =G25+F26
B27: =TODAY()+11 | C27: =LET(dt,B27,TEXT(dt,"dddd")) | D27: =LET( dt,B27, txDates,CashTransactions!B:B, txAmounts,CashTransactions!D:D, depMaturity,DepositsData!F:F, depPrincipal,DepositsData!D:D, depInterest,DepositsData!H:H, depStatus,DepositsData!G:G, cashIn,SUMIF(txDates,dt,txAmounts), depIn,SUMPRODUCT((depMaturity=dt)*(depStatus="Active")*(depPrincipal+depInterest)), MAX(0,cashIn)+depIn ) | E27: =LET( dt,B27, payDates,PaymentsData!B:B, payAmounts,PaymentsData!D:D, payStatus,PaymentsData!F:F, txDates,CashTransactions!B:B, txAmounts,CashTransactions!D:D, payments,SUMPRODUCT((payDates=dt)*(payStatus<>"Cancelled")*payAmounts), cashOut,ABS(MIN(0,SUMIF(txDates,dt,txAmounts))), payments+cashOut ) | F27: =D27-E27 | G27: =G26+F27
B28: =TODAY()+12 | C28: =LET(dt,B28,TEXT(dt,"dddd")) | D28: =LET( dt,B28, txDates,CashTransactions!B:B, txAmounts,CashTransactions!D:D, depMaturity,DepositsData!F:F, depPrincipal,DepositsData!D:D, depInterest,DepositsData!H:H, depStatus,DepositsData!G:G, cashIn,SUMIF(txDates,dt,txAmounts), depIn,SUMPRODUCT((depMaturity=dt)*(depStatus="Active")*(depPrincipal+depInterest)), MAX(0,cashIn)+depIn ) | E28: =LET( dt,B28, payDates,PaymentsData!B:B, payAmounts,PaymentsData!D:D, payStatus,PaymentsData!F:F, txDates,CashTransactions!B:B, txAmounts,CashTransactions!D:D, payments,SUMPRODUCT((payDates=dt)*(payStatus<>"Cancelled")*payAmounts), cashOut,ABS(MIN(0,SUMIF(txDates,dt,txAmounts))), payments+cashOut ) | F28: =D28-E28 | G28: =G27+F28
B29: =TODAY()+13 | C29: =LET(dt,B29,TEXT(dt,"dddd")) | D29: =LET( dt,B29, txDates,CashTransactions!B:B, txAmounts,CashTransactions!D:D, depMaturity,DepositsData!F:F, depPrincipal,DepositsData!D:D, depInterest,DepositsData!H:H, depStatus,DepositsData!G:G, cashIn,SUMIF(txDates,dt,txAmounts), depIn,SUMPRODUCT((depMaturity=dt)*(depStatus="Active")*(depPrincipal+depInterest)), MAX(0,cashIn)+depIn ) | E29: =LET( dt,B29, payDates,PaymentsData!B:B, payAmounts,PaymentsData!D:D, payStatus,PaymentsData!F:F, txDates,CashTransactions!B:B, txAmounts,CashTransactions!D:D, payments,SUMPRODUCT((payDates=dt)*(payStatus<>"Cancelled")*payAmounts), cashOut,ABS(MIN(0,SUMIF(txDates,dt,txAmounts))), payments+cashOut ) | F29: =D29-E29 | G29: =G28+F29
B32: Weekly Positions (Next 8 Weeks)
B33: Week Starting | C33: Week # | D33: Inflows | E33: Outflows | F33: Net | G33: End Balance
B34: =TODAY()-WEEKDAY(TODAY(),2)+1+0 | C34: =WEEKNUM(B34) | D34: =LET( startDt,B34, endDt,B34+6, txDates,CashTransactions!B:B, txAmounts,CashTransactions!D:D, depMaturity,DepositsData!F:F, depPrincipal,DepositsData!D:D, depInterest,DepositsData!H:H, depStatus,DepositsData!G:G, cashIn,SUMPRODUCT((txDates>=startDt)*(txDates<=endDt)*(txAmounts>0)*txAmounts), depIn,SUMPRODUCT((depMaturity>=startDt)*(depMaturity<=endDt)*(depStatus="Active")*(depPrincipal+depInterest)), cashIn+depIn ) | E34: =LET( startDt,B34, endDt,B34+6, payDates,PaymentsData!B:B, payAmounts,PaymentsData!D:D, payStatus,PaymentsData!F:F, txDates,CashTransactions!B:B, txAmounts,CashTransactions!D:D, payments,SUMPRODUCT((payDates>=startDt)*(payDates<=endDt)*(payStatus<>"Cancelled")*payAmounts), cashOut,ABS(SUMPRODUCT((txDates>=startDt)*(txDates<=endDt)*(txAmounts<0)*txAmounts)), payments+cashOut ) | F34: =D34-E34 | G34: =CashTransactions!J2+F34
B35: =TODAY()-WEEKDAY(TODAY(),2)+1+7 | C35: =WEEKNUM(B35) | D35: =LET( startDt,B35, endDt,B35+6, txDates,CashTransactions!B:B, txAmounts,CashTransactions!D:D, depMaturity,DepositsData!F:F, depPrincipal,DepositsData!D:D, depInterest,DepositsData!H:H, depStatus,DepositsData!G:G, cashIn,SUMPRODUCT((txDates>=startDt)*(txDates<=endDt)*(txAmounts>0)*txAmounts), depIn,SUMPRODUCT((depMaturity>=startDt)*(depMaturity<=endDt)*(depStatus="Active")*(depPrincipal+depInterest)), cashIn+depIn ) | E35: =LET( startDt,B35, endDt,B35+6, payDates,PaymentsData!B:B, payAmounts,PaymentsData!D:D, payStatus,PaymentsData!F:F, txDates,CashTransactions!B:B, txAmounts,CashTransactions!D:D, payments,SUMPRODUCT((payDates>=startDt)*(payDates<=endDt)*(payStatus<>"Cancelled")*payAmounts), cashOut,ABS(SUMPRODUCT((txDates>=startDt)*(txDates<=endDt)*(txAmounts<0)*txAmounts)), payments+cashOut ) | F35: =D35-E35 | G35: =G34+F35
B36: =TODAY()-WEEKDAY(TODAY(),2)+1+14 | C36: =WEEKNUM(B36) | D36: =LET( startDt,B36, endDt,B36+6, txDates,CashTransactions!B:B, txAmounts,CashTransactions!D:D, depMaturity,DepositsData!F:F, depPrincipal,DepositsData!D:D, depInterest,DepositsData!H:H, depStatus,DepositsData!G:G, cashIn,SUMPRODUCT((txDates>=startDt)*(txDates<=endDt)*(txAmounts>0)*txAmounts), depIn,SUMPRODUCT((depMaturity>=startDt)*(depMaturity<=endDt)*(depStatus="Active")*(depPrincipal+depInterest)), cashIn+depIn ) | E36: =LET( startDt,B36, endDt,B36+6, payDates,PaymentsData!B:B, payAmounts,PaymentsData!D:D, payStatus,PaymentsData!F:F, txDates,CashTransactions!B:B, txAmounts,CashTransactions!D:D, payments,SUMPRODUCT((payDates>=startDt)*(payDates<=endDt)*(payStatus<>"Cancelled")*payAmounts), cashOut,ABS(SUMPRODUCT((txDates>=startDt)*(txDates<=endDt)*(txAmounts<0)*txAmounts)), payments+cashOut ) | F36: =D36-E36 | G36: =G35+F36
B37: =TODAY()-WEEKDAY(TODAY(),2)+1+21 | C37: =WEEKNUM(B37) | D37: =LET( startDt,B37, endDt,B37+6, txDates,CashTransactions!B:B, txAmounts,CashTransactions!D:D, depMaturity,DepositsData!F:F, depPrincipal,DepositsData!D:D, depInterest,DepositsData!H:H, depStatus,DepositsData!G:G, cashIn,SUMPRODUCT((txDates>=startDt)*(txDates<=endDt)*(txAmounts>0)*txAmounts), depIn,SUMPRODUCT((depMaturity>=startDt)*(depMaturity<=endDt)*(depStatus="Active")*(depPrincipal+depInterest)), cashIn+depIn ) | E37: =LET( startDt,B37, endDt,B37+6, payDates,PaymentsData!B:B, payAmounts,PaymentsData!D:D, payStatus,PaymentsData!F:F, txDates,CashTransactions!B:B, txAmounts,CashTransactions!D:D, payments,SUMPRODUCT((payDates>=startDt)*(payDates<=endDt)*(payStatus<>"Cancelled")*payAmounts), cashOut,ABS(SUMPRODUCT((txDates>=startDt)*(txDates<=endDt)*(txAmounts<0)*txAmounts)), payments+cashOut ) | F37: =D37-E37 | G37: =G36+F37
B38: =TODAY()-WEEKDAY(TODAY(),2)+1+28 | C38: =WEEKNUM(B38) | D38: =LET( startDt,B38, endDt,B38+6, txDates,CashTransactions!B:B, txAmounts,CashTransactions!D:D, depMaturity,DepositsData!F:F, depPrincipal,DepositsData!D:D, depInterest,DepositsData!H:H, depStatus,DepositsData!G:G, cashIn,SUMPRODUCT((txDates>=startDt)*(txDates<=endDt)*(txAmounts>0)*txAmounts), depIn,SUMPRODUCT((depMaturity>=startDt)*(depMaturity<=endDt)*(depStatus="Active")*(depPrincipal+depInterest)), cashIn+depIn ) | E38: =LET( startDt,B38, endDt,B38+6, payDates,PaymentsData!B:B, payAmounts,PaymentsData!D:D, payStatus,PaymentsData!F:F, txDates,CashTransactions!B:B, txAmounts,CashTransactions!D:D, payments,SUMPRODUCT((payDates>=startDt)*(payDates<=endDt)*(payStatus<>"Cancelled")*payAmounts), cashOut,ABS(SUMPRODUCT((txDates>=startDt)*(txDates<=endDt)*(txAmounts<0)*txAmounts)), payments+cashOut ) | F38: =D38-E38 | G38: =G37+F38
B39: =TODAY()-WEEKDAY(TODAY(),2)+1+35 | C39: =WEEKNUM(B39) | D39: =LET( startDt,B39, endDt,B39+6, txDates,CashTransactions!B:B, txAmounts,CashTransactions!D:D, depMaturity,DepositsData!F:F, depPrincipal,DepositsData!D:D, depInterest,DepositsData!H:H, depStatus,DepositsData!G:G, cashIn,SUMPRODUCT((txDates>=startDt)*(txDates<=endDt)*(txAmounts>0)*txAmounts), depIn,SUMPRODUCT((depMaturity>=startDt)*(depMaturity<=endDt)*(depStatus="Active")*(depPrincipal+depInterest)), cashIn+depIn ) | E39: =LET( startDt,B39, endDt,B39+6, payDates,PaymentsData!B:B, payAmounts,PaymentsData!D:D, payStatus,PaymentsData!F:F, txDates,CashTransactions!B:B, txAmounts,CashTransactions!D:D, payments,SUMPRODUCT((payDates>=startDt)*(payDates<=endDt)*(payStatus<>"Cancelled")*payAmounts), cashOut,ABS(SUMPRODUCT((txDates>=startDt)*(txDates<=endDt)*(txAmounts<0)*txAmounts)), payments+cashOut ) | F39: =D39-E39 | G39: =G38+F39
B40: =TODAY()-WEEKDAY(TODAY(),2)+1+42 | C40: =WEEKNUM(B40) | D40: =LET( startDt,B40, endDt,B40+6, txDates,CashTransactions!B:B, txAmounts,CashTransactions!D:D, depMaturity,DepositsData!F:F, depPrincipal,DepositsData!D:D, depInterest,DepositsData!H:H, depStatus,DepositsData!G:G, cashIn,SUMPRODUCT((txDates>=startDt)*(txDates<=endDt)*(txAmounts>0)*txAmounts), depIn,SUMPRODUCT((depMaturity>=startDt)*(depMaturity<=endDt)*(depStatus="Active")*(depPrincipal+depInterest)), cashIn+depIn ) | E40: =LET( startDt,B40, endDt,B40+6, payDates,PaymentsData!B:B, payAmounts,PaymentsData!D:D, payStatus,PaymentsData!F:F, txDates,CashTransactions!B:B, txAmounts,CashTransactions!D:D, payments,SUMPRODUCT((payDates>=startDt)*(payDates<=endDt)*(payStatus<>"Cancelled")*payAmounts), cashOut,ABS(SUMPRODUCT((txDates>=startDt)*(txDates<=endDt)*(txAmounts<0)*txAmounts)), payments+cashOut ) | F40: =D40-E40 | G40: =G39+F40
B41: =TODAY()-WEEKDAY(TODAY(),2)+1+49 | C41: =WEEKNUM(B41) | D41: =LET( startDt,B41, endDt,B41+6, txDates,CashTransactions!B:B, txAmounts,CashTransactions!D:D, depMaturity,DepositsData!F:F, depPrincipal,DepositsData!D:D, depInterest,DepositsData!H:H, depStatus,DepositsData!G:G, cashIn,SUMPRODUCT((txDates>=startDt)*(txDates<=endDt)*(txAmounts>0)*txAmounts), depIn,SUMPRODUCT((depMaturity>=startDt)*(depMaturity<=endDt)*(depStatus="Active")*(depPrincipal+depInterest)), cashIn+depIn ) | E41: =LET( startDt,B41, endDt,B41+6, payDates,PaymentsData!B:B, payAmounts,PaymentsData!D:D, payStatus,PaymentsData!F:F, txDates,CashTransactions!B:B, txAmounts,CashTransactions!D:D, payments,SUMPRODUCT((payDates>=startDt)*(payDates<=endDt)*(payStatus<>"Cancelled")*payAmounts), cashOut,ABS(SUMPRODUCT((txDates>=startDt)*(txDates<=endDt)*(txAmounts<0)*txAmounts)), payments+cashOut ) | F41: =D41-E41 | G41: =G40+F41
B44: Monthly Positions (Next 6 Months)
B45: Month | C45: Inflows | D45: Outflows | E45: Net Flow | F45: End Balance | G45: Deposits Maturing
B46: =TEXT(EOMONTH(TODAY(),0),"MMMM YYYY") | C46: =LET( targetMonth,MONTH(EOMONTH(TODAY(),0)), targetYear,YEAR(EOMONTH(TODAY(),0)), txDates,CashTransactions!B:B, txAmounts,CashTransactions!D:D, cashIn,SUMPRODUCT((MONTH(txDates)=targetMonth)*(YEAR(txDates)=targetYear)*(txAmounts>0)*txAmounts), cashIn ) | D46: =LET( targetMonth,MONTH(EOMONTH(TODAY(),0)), targetYear,YEAR(EOMONTH(TODAY(),0)), payDates,PaymentsData!B:B, payAmounts,PaymentsData!D:D, payStatus,PaymentsData!F:F, payments,SUMPRODUCT((MONTH(payDates)=targetMonth)*(YEAR(payDates)=targetYear)*(payStatus<>"Cancelled")*payAmounts), payments ) | E46: =C46-D46 | F46: =CashTransactions!J2+E46 | G46: =LET( targetMonth,MONTH(EOMONTH(TODAY(),0)), targetYear,YEAR(EOMONTH(TODAY(),0)), depMaturity,DepositsData!F:F, depPrincipal,DepositsData!D:D, depInterest,DepositsData!H:H, depStatus,DepositsData!G:G, SUMPRODUCT((MONTH(depMaturity)=targetMonth)*(YEAR(depMaturity)=targetYear)*(depStatus="Active")*(depPrincipal+depInterest)) )
B47: =TEXT(EOMONTH(TODAY(),1),"MMMM YYYY") | C47: =LET( targetMonth,MONTH(EOMONTH(TODAY(),1)), targetYear,YEAR(EOMONTH(TODAY(),1)), txDates,CashTransactions!B:B, txAmounts,CashTransactions!D:D, cashIn,SUMPRODUCT((MONTH(txDates)=targetMonth)*(YEAR(txDates)=targetYear)*(txAmounts>0)*txAmounts), cashIn ) | D47: =LET( targetMonth,MONTH(EOMONTH(TODAY(),1)), targetYear,YEAR(EOMONTH(TODAY(),1)), payDates,PaymentsData!B:B, payAmounts,PaymentsData!D:D, payStatus,PaymentsData!F:F, payments,SUMPRODUCT((MONTH(payDates)=targetMonth)*(YEAR(payDates)=targetYear)*(payStatus<>"Cancelled")*payAmounts), payments ) | E47: =C47-D47 | F47: =F46+E47 | G47: =LET( targetMonth,MONTH(EOMONTH(TODAY(),1)), targetYear,YEAR(EOMONTH(TODAY(),1)), depMaturity,DepositsData!F:F, depPrincipal,DepositsData!D:D, depInterest,DepositsData!H:H, depStatus,DepositsData!G:G, SUMPRODUCT((MONTH(depMaturity)=targetMonth)*(YEAR(depMaturity)=targetYear)*(depStatus="Active")*(depPrincipal+depInterest)) )
B48: =TEXT(EOMONTH(TODAY(),2),"MMMM YYYY") | C48: =LET( targetMonth,MONTH(EOMONTH(TODAY(),2)), targetYear,YEAR(EOMONTH(TODAY(),2)), txDates,CashTransactions!B:B, txAmounts,CashTransactions!D:D, cashIn,SUMPRODUCT((MONTH(txDates)=targetMonth)*(YEAR(txDates)=targetYear)*(txAmounts>0)*txAmounts), cashIn ) | D48: =LET( targetMonth,MONTH(EOMONTH(TODAY(),2)), targetYear,YEAR(EOMONTH(TODAY(),2)), payDates,PaymentsData!B:B, payAmounts,PaymentsData!D:D, payStatus,PaymentsData!F:F, payments,SUMPRODUCT((MONTH(payDates)=targetMonth)*(YEAR(payDates)=targetYear)*(payStatus<>"Cancelled")*payAmounts), payments ) | E48: =C48-D48 | F48: =F47+E48 | G48: =LET( targetMonth,MONTH(EOMONTH(TODAY(),2)), targetYear,YEAR(EOMONTH(TODAY(),2)), depMaturity,DepositsData!F:F, depPrincipal,DepositsData!D:D, depInterest,DepositsData!H:H, depStatus,DepositsData!G:G, SUMPRODUCT((MONTH(depMaturity)=targetMonth)*(YEAR(depMaturity)=targetYear)*(depStatus="Active")*(depPrincipal+depInterest)) )
B49: =TEXT(EOMONTH(TODAY(),3),"MMMM YYYY") | C49: =LET( targetMonth,MONTH(EOMONTH(TODAY(),3)), targetYear,YEAR(EOMONTH(TODAY(),3)), txDates,CashTransactions!B:B, txAmounts,CashTransactions!D:D, cashIn,SUMPRODUCT((MONTH(txDates)=targetMonth)*(YEAR(txDates)=targetYear)*(txAmounts>0)*txAmounts), cashIn ) | D49: =LET( targetMonth,MONTH(EOMONTH(TODAY(),3)), targetYear,YEAR(EOMONTH(TODAY(),3)), payDates,PaymentsData!B:B, payAmounts,PaymentsData!D:D, payStatus,PaymentsData!F:F, payments,SUMPRODUCT((MONTH(payDates)=targetMonth)*(YEAR(payDates)=targetYear)*(payStatus<>"Cancelled")*payAmounts), payments ) | E49: =C49-D49 | F49: =F48+E49 | G49: =LET( targetMonth,MONTH(EOMONTH(TODAY(),3)), targetYear,YEAR(EOMONTH(TODAY(),3)), depMaturity,DepositsData!F:F, depPrincipal,DepositsData!D:D, depInterest,DepositsData!H:H, depStatus,DepositsData!G:G, SUMPRODUCT((MONTH(depMaturity)=targetMonth)*(YEAR(depMaturity)=targetYear)*(depStatus="Active")*(depPrincipal+depInterest)) )
B50: =TEXT(EOMONTH(TODAY(),4),"MMMM YYYY") | C50: =LET( targetMonth,MONTH(EOMONTH(TODAY(),4)), targetYear,YEAR(EOMONTH(TODAY(),4)), txDates,CashTransactions!B:B, txAmounts,CashTransactions!D:D, cashIn,SUMPRODUCT((MONTH(txDates)=targetMonth)*(YEAR(txDates)=targetYear)*(txAmounts>0)*txAmounts), cashIn ) | D50: =LET( targetMonth,MONTH(EOMONTH(TODAY(),4)), targetYear,YEAR(EOMONTH(TODAY(),4)), payDates,PaymentsData!B:B, payAmounts,PaymentsData!D:D, payStatus,PaymentsData!F:F, payments,SUMPRODUCT((MONTH(payDates)=targetMonth)*(YEAR(payDates)=targetYear)*(payStatus<>"Cancelled")*payAmounts), payments ) | E50: =C50-D50 | F50: =F49+E50 | G50: =LET( targetMonth,MONTH(EOMONTH(TODAY(),4)), targetYear,YEAR(EOMONTH(TODAY(),4)), depMaturity,DepositsData!F:F, depPrincipal,DepositsData!D:D, depInterest,DepositsData!H:H, depStatus,DepositsData!G:G, SUMPRODUCT((MONTH(depMaturity)=targetMonth)*(YEAR(depMaturity)=targetYear)*(depStatus="Active")*(depPrincipal+depInterest)) )
B51: =TEXT(EOMONTH(TODAY(),5),"MMMM YYYY") | C51: =LET( targetMonth,MONTH(EOMONTH(TODAY(),5)), targetYear,YEAR(EOMONTH(TODAY(),5)), txDates,CashTransactions!B:B, txAmounts,CashTransactions!D:D, cashIn,SUMPRODUCT((MONTH(txDates)=targetMonth)*(YEAR(txDates)=targetYear)*(txAmounts>0)*txAmounts), cashIn ) | D51: =LET( targetMonth,MONTH(EOMONTH(TODAY(),5)), targetYear,YEAR(EOMONTH(TODAY(),5)), payDates,PaymentsData!B:B, payAmounts,PaymentsData!D:D, payStatus,PaymentsData!F:F, payments,SUMPRODUCT((MONTH(payDates)=targetMonth)*(YEAR(payDates)=targetYear)*(payStatus<>"Cancelled")*payAmounts), payments ) | E51: =C51-D51 | F51: =F50+E51 | G51: =LET( targetMonth,MONTH(EOMONTH(TODAY(),5)), targetYear,YEAR(EOMONTH(TODAY(),5)), depMaturity,DepositsData!F:F, depPrincipal,DepositsData!D:D, depInterest,DepositsData!H:H, depStatus,DepositsData!G:G, SUMPRODUCT((MONTH(depMaturity)=targetMonth)*(YEAR(depMaturity)=targetYear)*(depStatus="Active")*(depPrincipal+depInterest)) )

Sheet PaymentsData
A1: Payment ID | B1: Due Date | C1: Payee | D1: Amount | E1: Category | F1: Status | G1: Notes
A2: PAY001 | B2: 46005.706 | C2: ABC Suppliers | D2: 15000 | E2: Vendor | F2: Scheduled | G2: Monthly supplies
A3: PAY002 | B3: 46008.706 | C3: City Utilities | D3: 3500 | E3: Utilities | F3: Pending | G3: Electric & Water
A4: PAY003 | B4: 46010.706 | C4: Office Rent LLC | D4: 25000 | E4: Rent | F4: Scheduled | G4: Monthly rent
A5: PAY004 | B5: 46013.706 | C5: Insurance Co. | D5: 5000 | E5: Insurance | F5: Scheduled | G5: Quarterly premium
A6: PAY005 | B6: 46015.706 | C6: Payroll | D6: 85000 | E6: Payroll | F6: Scheduled | G6: Bi-weekly payroll
A7: PAY006 | B7: 46018.706 | C7: Tech Solutions | D7: 8500 | E7: Services | F7: Pending | G7: IT support
A8: PAY007 | B8: 46021.706 | C8: Marketing Agency | D8: 12000 | E8: Services | F8: Scheduled | G8: Monthly retainer
A9: PAY008 | B9: 46023.706 | C9: Office Supplies Inc | D9: 2500 | E9: Supplies | F9: Scheduled | G9: Office materials
A10: PAY009 | B10: 46000.706 | C10: Contractor XYZ | D10: 7500 | E10: Services | F10: Overdue | G10: Project milestone
A11: PAY010 | B11: 45998.706 | C11: Equipment Lease | D11: 4000 | E11: Other | F11: Paid | G11: Monthly lease
A12: PAY011 | B12: 46028.706 | C12: Payroll | D12: 85000 | E12: Payroll | F12: Scheduled | G12: Bi-weekly payroll
A13: PAY012 | B13: 46031.706 | C13: Tax Authority | D13: 45000 | E13: Taxes | F13: Scheduled | G13: Quarterly taxes

Sheet DepositsData
A1: Deposit ID | B1: Bank/Institution | C1: Start Date | D1: Principal | E1: Rate | F1: Maturity Date | G1: Status | H1: Interest | I1: Notes
A2: TD001 | B2: First National Bank | C2: 45913.706 | D2: 500000 | E2: 0.045 | F2: 46093.706 | G2: Active | H2: =LET(p,D2,r,E2,start,C2,maturity,F2,days,maturity-start,p*r*days/365) | I2: 6-month CD
A3: TD002 | B3: City Credit Union | C3: 45943.706 | D3: 250000 | E3: 0.0425 | F3: 46123.706 | G3: Active | H3: =LET(p,D3,r,E3,start,C3,maturity,F3,days,maturity-start,p*r*days/365) | I3: 6-month term
A4: TD003 | B4: State Bank | C4: 45973.706 | D4: 750000 | E4: 0.05 | F4: 46338.706 | G4: Active | H4: =LET(p,D4,r,E4,start,C4,maturity,F4,days,maturity-start,p*r*days/365) | I4: 12-month CD
A5: TD004 | B5: Federal Savings | C5: 45823.706 | D5: 300000 | E5: 0.04 | F5: 46008.706 | G5: Active | H5: =LET(p,D5,r,E5,start,C5,maturity,F5,days,maturity-start,p*r*days/365) | I5: Maturing soon
A6: TD005 | B6: Capital One | C6: 45883.706 | D6: 400000 | E6: 0.0475 | F6: 46063.706 | G6: Active | H6: =LET(p,D6,r,E6,start,C6,maturity,F6,days,maturity-start,p*r*days/365) | I6: 6-month CD
A7: TD006 | B7: Wells Fargo | C7: 45638.706 | D7: 200000 | E7: 0.035 | F7: 45998.706 | G7: Matured | H7: =LET(p,D7,r,E7,start,C7,maturity,F7,days,maturity-start,p*r*days/365) | I7: Awaiting reinvestment
A8: TD007 | B8: Chase Bank | C8: 45958.706 | D8: 600000 | E8: 0.0525 | F8: 46138.706 | G8: Active | H8: =LET(p,D8,r,E8,start,C8,maturity,F8,days,maturity-start,p*r*days/365) | I8: 6-month CD
A9: TD008 | B9: Bank of America | C9: 45988.706 | D9: 350000 | E9: 0.048 | F9: 46168.706 | G9: Active | H9: =LET(p,D9,r,E9,start,C9,maturity,F9,days,maturity-start,p*r*days/365) | I9: 6-month term

Sheet CashTransactions
A1: Trans ID | B1: Date | C1: Type | D1: Amount | E1: Description | F1: Category | G1: Account | H1: Reference | I1: Notes | J1: Running Balance
A2: TRX001 | B2: 45993.706 | C2: Inflow | D2: 150000 | E2: Customer Payment - ABC Corp | F2: Revenue | G2: Operating | H2: INV-2024-001 | J2: 2650000
A3: TRX002 | B3: 45994.706 | C3: Outflow | D3: -45000 | E3: Supplier Payment | F3: COGS | G3: Operating | H3: PO-2024-123 | J3: 2605000
A4: TRX003 | B4: 45995.706 | C4: Inflow | D4: 200000 | E4: Customer Payment - XYZ Inc | F4: Revenue | G4: Operating | H4: INV-2024-002 | J4: 2805000
A5: TRX004 | B5: 45996.706 | C5: Outflow | D5: -85000 | E5: Payroll | F5: Payroll | G5: Operating | H5: PR-2024-24 | I5: Bi-weekly | J5: 2720000
A6: TRX005 | B6: 45998.706 | C6: Inflow | D6: 75000 | E6: Customer Payment - DEF Ltd | F6: Revenue | G6: Operating | H6: INV-2024-003 | J6: 2795000
A7: TRX006 | B7: 45999.706 | C7: Outflow | D7: -25000 | E7: Office Rent | F7: Rent | G7: Operating | H7: RENT-DEC | I7: Monthly | J7: 2770000
A8: TRX007 | B8: 46000.706 | C8: Inflow | D8: 500000 | E8: TD Maturity - Wells Fargo | F8: Interest | G8: Investments | H8: TD006 | I8: Plus interest | J8: 3270000
A9: TRX008 | B9: 46001.706 | C9: Outflow | D9: -350000 | E9: New Time Deposit | F9: Investment | G9: Investments | H9: TD008 | I9: 6-month term | J9: 2920000
A10: TRX009 | B10: 46002.706 | C10: Inflow | D10: 125000 | E10: Customer Payment - GHI Co | F10: Revenue | G10: Operating | H10: INV-2024-004 | J10: 3045000
A11: TRX010 | B11: 46003.706 | C11: Outflow | D11: -15000 | E11: Utility Bills | F11: Utilities | G11: Operating | H11: UTIL-DEC | I11: Electric, Water, Gas | J11: 3030000

Sheet Settings
B2: Settings & Configuration
B4: Company Information
B5: Company Name: | C5: Your Company Name
B6: Currency: | C6: USD
B7: Fiscal Year Start: | C7: January
B8: Default Payment Terms: | C8: Net 30
B11: Payment Categories | D11: Status Definitions
B12: Payroll | D12: Scheduled | E12: Future payment, not yet processed
B13: Vendor | D13: Pending | E13: Payment initiated, awaiting completion
B14: Utilities | D14: Paid | E14: Payment completed successfully
B15: Rent | D15: Overdue | E15: Payment past due date
B16: Insurance | D16: Cancelled | E16: Payment cancelled
B17: Taxes
B18: Supplies
B19: Services
B20: Other
B22: Alert Thresholds
B23: Minimum Cash Balance: | C23: 100000 | D23: Alert when balance falls below
B24: Days Before Maturity Alert: | C24: 30 | D24: Days before deposit maturity
B25: Days Before Payment Due: | C25: 7 | D25: Days before payment reminder
B28: Modern Formula Reference
B29: LET | C29: Defines named variables within formulas for clarity
B30: FILTER | C30: Returns array of values that meet criteria
B31: XLOOKUP | C31: Modern replacement for VLOOKUP/INDEX-MATCH
B32: SORT | C32: Sorts array by specified column
B33: HSTACK | C33: Horizontally stacks arrays into single array
B34: LAMBDA | C34: Creates custom reusable functions
